{"0":{"city_order":25,"city_id":52025,"city_pref_name":"\u4eac\u90fd\u5e9c","city_name":"\u6728\u6d25\u5ddd\u5e02","city_pref":52,"city_detail":"","zip_code":"6190200"},"1":{"city_order":32,"city_id":52032,"city_pref_name":"\u4eac\u90fd\u5e9c","city_name":"\u76f8\u697d\u90e1\u7cbe\u83ef\u753a","city_pref":52,"city_detail":"","zip_code":"6190200"},"2":{"city_order":25,"city_id":52025,"city_pref_name":"\u4eac\u90fd\u5e9c","city_name":"\u6728\u6d25\u5ddd\u5e02","city_pref":52,"city_detail":"\u5c71\u57ce\u753a\u7dba\u7530","zip_code":"6190201"},"3":{"city_order":25,"city_id":52025,"city_pref_name":"\u4eac\u90fd\u5e9c","city_name":"\u6728\u6d25\u5ddd\u5e02","city_pref":52,"city_detail":"\u5c71\u57ce\u753a\u5e73\u5c3e","zip_code":"6190202"},"4":{"city_order":25,"city_id":52025,"city_pref_name":"\u4eac\u90fd\u5e9c","city_name":"\u6728\u6d25\u5ddd\u5e02","city_pref":52,"city_detail":"\u5c71\u57ce\u753a\u795e\u7ae5\u5b50","zip_code":"6190203"},"5":{"city_order":25,"city_id":52025,"city_pref_name":"\u4eac\u90fd\u5e9c","city_name":"\u6728\u6d25\u5ddd\u5e02","city_pref":52,"city_detail":"\u5c71\u57ce\u753a\u4e0a\u72db","zip_code":"6190204"},"6":{"city_order":25,"city_id":52025,"city_pref_name":"\u4eac\u90fd\u5e9c","city_name":"\u6728\u6d25\u5ddd\u5e02","city_pref":52,"city_detail":"\u5c71\u57ce\u753a\u693f\u4e95","zip_code":"6190205"},"7":{"city_order":25,"city_id":52025,"city_pref_name":"\u4eac\u90fd\u5e9c","city_name":"\u6728\u6d25\u5ddd\u5e02","city_pref":52,"city_detail":"\u5c71\u57ce\u753a\u5317\u6cb3\u539f","zip_code":"6190206"},"8":{"city_order":25,"city_id":52025,"city_pref_name":"\u4eac\u90fd\u5e9c","city_name":"\u6728\u6d25\u5ddd\u5e02","city_pref":52,"city_detail":"\u9e7f\u80cc\u5c71","zip_code":"6190211"},"9":{"city_order":25,"city_id":52025,"city_pref_name":"\u4eac\u90fd\u5e9c","city_name":"\u6728\u6d25\u5ddd\u5e02","city_pref":52,"city_detail":"\u6885\u8c37","zip_code":"6190212"},"10":{"city_order":25,"city_id":52025,"city_pref_name":"\u4eac\u90fd\u5e9c","city_name":"\u6728\u6d25\u5ddd\u5e02","city_pref":52,"city_detail":"\u5e02\u5742","zip_code":"6190213"},"11":{"city_order":25,"city_id":52025,"city_pref_name":"\u4eac\u90fd\u5e9c","city_name":"\u6728\u6d25\u5ddd\u5e02","city_pref":52,"city_detail":"\u6728\u6d25","zip_code":"6190214"},"12":{"city_order":25,"city_id":52025,"city_pref_name":"\u4eac\u90fd\u5e9c","city_name":"\u6728\u6d25\u5ddd\u5e02","city_pref":52,"city_detail":"\u6885\u7f8e\u53f0","zip_code":"6190215"},"13":{"city_order":25,"city_id":52025,"city_pref_name":"\u4eac\u90fd\u5e9c","city_name":"\u6728\u6d25\u5ddd\u5e02","city_pref":52,"city_detail":"\u5dde\u898b\u53f0","zip_code":"6190216"},"14":{"city_order":25,"city_id":52025,"city_pref_name":"\u4eac\u90fd\u5e9c","city_name":"\u6728\u6d25\u5ddd\u5e02","city_pref":52,"city_detail":"\u6728\u6d25\u753a","zip_code":"6190217"},"15":{"city_order":25,"city_id":52025,"city_pref_name":"\u4eac\u90fd\u5e9c","city_name":"\u6728\u6d25\u5ddd\u5e02","city_pref":52,"city_detail":"\u5410\u5e2b","zip_code":"6190221"},"16":{"city_order":25,"city_id":52025,"city_pref_name":"\u4eac\u90fd\u5e9c","city_name":"\u6728\u6d25\u5ddd\u5e02","city_pref":52,"city_detail":"\u76f8\u697d","zip_code":"6190222"},"17":{"city_order":25,"city_id":52025,"city_pref_name":"\u4eac\u90fd\u5e9c","city_name":"\u6728\u6d25\u5ddd\u5e02","city_pref":52,"city_detail":"\u76f8\u697d\u53f0","zip_code":"6190223"},"18":{"city_order":25,"city_id":52025,"city_pref_name":"\u4eac\u90fd\u5e9c","city_name":"\u6728\u6d25\u5ddd\u5e02","city_pref":52,"city_detail":"\u515c\u53f0","zip_code":"6190224"},"19":{"city_order":25,"city_id":52025,"city_pref_name":"\u4eac\u90fd\u5e9c","city_name":"\u6728\u6d25\u5ddd\u5e02","city_pref":52,"city_detail":"\u6728\u6d25\u5ddd\u53f0","zip_code":"6190225"},"20":{"city_order":32,"city_id":52032,"city_pref_name":"\u4eac\u90fd\u5e9c","city_name":"\u76f8\u697d\u90e1\u7cbe\u83ef\u753a","city_pref":52,"city_detail":"\u5c71\u7530","zip_code":"6190231"},"21":{"city_order":32,"city_id":52032,"city_pref_name":"\u4eac\u90fd\u5e9c","city_name":"\u76f8\u697d\u90e1\u7cbe\u83ef\u753a","city_pref":52,"city_detail":"\u685c\u304c\u4e18","zip_code":"6190232"},"22":{"city_order":32,"city_id":52032,"city_pref_name":"\u4eac\u90fd\u5e9c","city_name":"\u76f8\u697d\u90e1\u7cbe\u83ef\u753a","city_pref":52,"city_detail":"\u4e7e\u8c37","zip_code":"6190233"},"23":{"city_order":32,"city_id":52032,"city_pref_name":"\u4eac\u90fd\u5e9c","city_name":"\u76f8\u697d\u90e1\u7cbe\u83ef\u753a","city_pref":52,"city_detail":"\u67d8\u69b4","zip_code":"6190234"},"24":{"city_order":32,"city_id":52032,"city_pref_name":"\u4eac\u90fd\u5e9c","city_name":"\u76f8\u697d\u90e1\u7cbe\u83ef\u753a","city_pref":52,"city_detail":"\u6771\u7551","zip_code":"6190235"},"25":{"city_order":32,"city_id":52032,"city_pref_name":"\u4eac\u90fd\u5e9c","city_name":"\u76f8\u697d\u90e1\u7cbe\u83ef\u753a","city_pref":52,"city_detail":"\u690d\u7530","zip_code":"6190236"},"26":{"city_order":32,"city_id":52032,"city_pref_name":"\u4eac\u90fd\u5e9c","city_name":"\u76f8\u697d\u90e1\u7cbe\u83ef\u753a","city_pref":52,"city_detail":"\u5149\u53f0","zip_code":"6190237"},"27":{"city_order":32,"city_id":52032,"city_pref_name":"\u4eac\u90fd\u5e9c","city_name":"\u76f8\u697d\u90e1\u7cbe\u83ef\u753a","city_pref":52,"city_detail":"\u7cbe\u83ef\u53f0","zip_code":"6190238"},"28":{"city_order":32,"city_id":52032,"city_pref_name":"\u4eac\u90fd\u5e9c","city_name":"\u76f8\u697d\u90e1\u7cbe\u83ef\u753a","city_pref":52,"city_detail":"\u795d\u5712\u897f","zip_code":"6190240"},"29":{"city_order":32,"city_id":52032,"city_pref_name":"\u4eac\u90fd\u5e9c","city_name":"\u76f8\u697d\u90e1\u7cbe\u83ef\u753a","city_pref":52,"city_detail":"\u795d\u5712","zip_code":"6190241"},"30":{"city_order":32,"city_id":52032,"city_pref_name":"\u4eac\u90fd\u5e9c","city_name":"\u76f8\u697d\u90e1\u7cbe\u83ef\u753a","city_pref":52,"city_detail":"\u83c5\u4e95","zip_code":"6190242"},"31":{"city_order":32,"city_id":52032,"city_pref_name":"\u4eac\u90fd\u5e9c","city_name":"\u76f8\u697d\u90e1\u7cbe\u83ef\u753a","city_pref":52,"city_detail":"\u5357\u7a32\u516b\u59bb","zip_code":"6190243"},"32":{"city_order":32,"city_id":52032,"city_pref_name":"\u4eac\u90fd\u5e9c","city_name":"\u76f8\u697d\u90e1\u7cbe\u83ef\u753a","city_pref":52,"city_detail":"\u5317\u7a32\u516b\u9593","zip_code":"6190244"},"33":{"city_order":32,"city_id":52032,"city_pref_name":"\u4eac\u90fd\u5e9c","city_name":"\u76f8\u697d\u90e1\u7cbe\u83ef\u753a","city_pref":52,"city_detail":"\u4e0b\u72db","zip_code":"6190245"},"34":{"city_order":32,"city_id":52032,"city_pref_name":"\u4eac\u90fd\u5e9c","city_name":"\u76f8\u697d\u90e1\u7cbe\u83ef\u753a","city_pref":52,"city_detail":"\u83f1\u7530","zip_code":"6190246"},"35":{"city_order":25,"city_id":52025,"city_pref_name":"\u4eac\u90fd\u5e9c","city_name":"\u6728\u6d25\u5ddd\u5e02","city_pref":52,"city_detail":"\u52a0\u8302\u753a\u92ad\u53f8","zip_code":"6191101"},"36":{"city_order":25,"city_id":52025,"city_pref_name":"\u4eac\u90fd\u5e9c","city_name":"\u6728\u6d25\u5ddd\u5e02","city_pref":52,"city_detail":"\u52a0\u8302\u753a\u4e95\u5e73\u5c3e","zip_code":"6191102"},"37":{"city_order":25,"city_id":52025,"city_pref_name":"\u4eac\u90fd\u5e9c","city_name":"\u6728\u6d25\u5ddd\u5e02","city_pref":52,"city_detail":"\u52a0\u8302\u753a\u5ca1\u5d0e","zip_code":"6191103"},"38":{"city_order":25,"city_id":52025,"city_pref_name":"\u4eac\u90fd\u5e9c","city_name":"\u6728\u6d25\u5ddd\u5e02","city_pref":52,"city_detail":"\u52a0\u8302\u753a\u6cb3\u539f","zip_code":"6191104"},"39":{"city_order":25,"city_id":52025,"city_pref_name":"\u4eac\u90fd\u5e9c","city_name":"\u6728\u6d25\u5ddd\u5e02","city_pref":52,"city_detail":"\u52a0\u8302\u753a\u897f","zip_code":"6191105"},"40":{"city_order":25,"city_id":52025,"city_pref_name":"\u4eac\u90fd\u5e9c","city_name":"\u6728\u6d25\u5ddd\u5e02","city_pref":52,"city_detail":"\u52a0\u8302\u753a\u4f8b\u5e63","zip_code":"6191106"},"41":{"city_order":25,"city_id":52025,"city_pref_name":"\u4eac\u90fd\u5e9c","city_name":"\u6728\u6d25\u5ddd\u5e02","city_pref":52,"city_detail":"\u52a0\u8302\u753a\u5965\u7551","zip_code":"6191107"},"42":{"city_order":25,"city_id":52025,"city_pref_name":"\u4eac\u90fd\u5e9c","city_name":"\u6728\u6d25\u5ddd\u5e02","city_pref":52,"city_detail":"\u52a0\u8302\u753a\u5c71\u7530","zip_code":"6191111"},"43":{"city_order":25,"city_id":52025,"city_pref_name":"\u4eac\u90fd\u5e9c","city_name":"\u6728\u6d25\u5ddd\u5e02","city_pref":52,"city_detail":"\u52a0\u8302\u753a\u514e\u4e26","zip_code":"6191112"},"44":{"city_order":25,"city_id":52025,"city_pref_name":"\u4eac\u90fd\u5e9c","city_name":"\u6728\u6d25\u5ddd\u5e02","city_pref":52,"city_detail":"\u52a0\u8302\u753a\u5317","zip_code":"6191113"},"45":{"city_order":25,"city_id":52025,"city_pref_name":"\u4eac\u90fd\u5e9c","city_name":"\u6728\u6d25\u5ddd\u5e02","city_pref":52,"city_detail":"\u52a0\u8302\u753a\u5317\u4e0b\u624b","zip_code":"6191121"},"46":{"city_order":25,"city_id":52025,"city_pref_name":"\u4eac\u90fd\u5e9c","city_name":"\u6728\u6d25\u5ddd\u5e02","city_pref":52,"city_detail":"\u52a0\u8302\u753a\u5357\u4e0b\u624b","zip_code":"6191122"},"47":{"city_order":25,"city_id":52025,"city_pref_name":"\u4eac\u90fd\u5e9c","city_name":"\u6728\u6d25\u5ddd\u5e02","city_pref":52,"city_detail":"\u52a0\u8302\u753a\u68ee","zip_code":"6191123"},"48":{"city_order":25,"city_id":52025,"city_pref_name":"\u4eac\u90fd\u5e9c","city_name":"\u6728\u6d25\u5ddd\u5e02","city_pref":52,"city_detail":"\u52a0\u8302\u753a\u52dd\u98a8","zip_code":"6191124"},"49":{"city_order":25,"city_id":52025,"city_pref_name":"\u4eac\u90fd\u5e9c","city_name":"\u6728\u6d25\u5ddd\u5e02","city_pref":52,"city_detail":"\u52a0\u8302\u753a\u9ad8\u53bb","zip_code":"6191125"},"50":{"city_order":25,"city_id":52025,"city_pref_name":"\u4eac\u90fd\u5e9c","city_name":"\u6728\u6d25\u5ddd\u5e02","city_pref":52,"city_detail":"\u52a0\u8302\u753a\u5c3b\u679d","zip_code":"6191126"},"51":{"city_order":25,"city_id":52025,"city_pref_name":"\u4eac\u90fd\u5e9c","city_name":"\u6728\u6d25\u5ddd\u5e02","city_pref":52,"city_detail":"\u5357\u52a0\u8302\u53f0","zip_code":"6191127"},"52":{"city_order":25,"city_id":52025,"city_pref_name":"\u4eac\u90fd\u5e9c","city_name":"\u6728\u6d25\u5ddd\u5e02","city_pref":52,"city_detail":"\u52a0\u8302\u753a\u8fbb","zip_code":"6191131"},"53":{"city_order":25,"city_id":52025,"city_pref_name":"\u4eac\u90fd\u5e9c","city_name":"\u6728\u6d25\u5ddd\u5e02","city_pref":52,"city_detail":"\u52a0\u8302\u753a\u5927\u7551","zip_code":"6191132"},"54":{"city_order":25,"city_id":52025,"city_pref_name":"\u4eac\u90fd\u5e9c","city_name":"\u6728\u6d25\u5ddd\u5e02","city_pref":52,"city_detail":"\u52a0\u8302\u753a\u5ca9\u8239","zip_code":"6191133"},"55":{"city_order":25,"city_id":52025,"city_pref_name":"\u4eac\u90fd\u5e9c","city_name":"\u6728\u6d25\u5ddd\u5e02","city_pref":52,"city_detail":"\u52a0\u8302\u753a\u6771\u5c0f\u4e0a","zip_code":"6191134"},"56":{"city_order":25,"city_id":52025,"city_pref_name":"\u4eac\u90fd\u5e9c","city_name":"\u6728\u6d25\u5ddd\u5e02","city_pref":52,"city_detail":"\u52a0\u8302\u753a\u6771\u5c0f\u4e0b","zip_code":"6191134"},"57":{"city_order":25,"city_id":52025,"city_pref_name":"\u4eac\u90fd\u5e9c","city_name":"\u6728\u6d25\u5ddd\u5e02","city_pref":52,"city_detail":"\u52a0\u8302\u753a\u897f\u5c0f","zip_code":"6191135"},"58":{"city_order":25,"city_id":52025,"city_pref_name":"\u4eac\u90fd\u5e9c","city_name":"\u6728\u6d25\u5ddd\u5e02","city_pref":52,"city_detail":"\u52a0\u8302\u753a\u5317\u5927\u9580","zip_code":"6191136"},"59":{"city_order":25,"city_id":52025,"city_pref_name":"\u4eac\u90fd\u5e9c","city_name":"\u6728\u6d25\u5ddd\u5e02","city_pref":52,"city_detail":"\u52a0\u8302\u753a\u5357\u5927\u9580","zip_code":"6191136"},"60":{"city_order":25,"city_id":52025,"city_pref_name":"\u4eac\u90fd\u5e9c","city_name":"\u6728\u6d25\u5ddd\u5e02","city_pref":52,"city_detail":"\u52a0\u8302\u753a\u6cd5\u82b1\u5bfa\u91ce","zip_code":"6191141"},"61":{"city_order":25,"city_id":52025,"city_pref_name":"\u4eac\u90fd\u5e9c","city_name":"\u6728\u6d25\u5ddd\u5e02","city_pref":52,"city_detail":"\u52a0\u8302\u753a\u5927\u91ce","zip_code":"6191142"},"62":{"city_order":25,"city_id":52025,"city_pref_name":"\u4eac\u90fd\u5e9c","city_name":"\u6728\u6d25\u5ddd\u5e02","city_pref":52,"city_detail":"\u52a0\u8302\u753a\u89b3\u97f3\u5bfa","zip_code":"6191143"},"63":{"city_order":25,"city_id":52025,"city_pref_name":"\u4eac\u90fd\u5e9c","city_name":"\u6728\u6d25\u5ddd\u5e02","city_pref":52,"city_detail":"\u52a0\u8302\u753a\u9ad8\u7530","zip_code":"6191144"},"64":{"city_order":25,"city_id":52025,"city_pref_name":"\u4eac\u90fd\u5e9c","city_name":"\u6728\u6d25\u5ddd\u5e02","city_pref":52,"city_detail":"\u52a0\u8302\u753a\u7f8e\u6d6a","zip_code":"6191151"},"65":{"city_order":25,"city_id":52025,"city_pref_name":"\u4eac\u90fd\u5e9c","city_name":"\u6728\u6d25\u5ddd\u5e02","city_pref":52,"city_detail":"\u52a0\u8302\u753a\u91cc","zip_code":"6191152"},"66":{"city_order":25,"city_id":52025,"city_pref_name":"\u4eac\u90fd\u5e9c","city_name":"\u6728\u6d25\u5ddd\u5e02","city_pref":52,"city_detail":"\u52a0\u8302\u753a\u99c5\u897f","zip_code":"6191153"},"67":{"city_order":25,"city_id":52025,"city_pref_name":"\u4eac\u90fd\u5e9c","city_name":"\u6728\u6d25\u5ddd\u5e02","city_pref":52,"city_detail":"\u52a0\u8302\u753a\u99c5\u6771","zip_code":"6191154"},"68":{"city_order":31,"city_id":52031,"city_pref_name":"\u4eac\u90fd\u5e9c","city_name":"\u76f8\u697d\u90e1\u548c\u675f\u753a","city_pref":52,"city_detail":"","zip_code":"6191200"},"69":{"city_order":31,"city_id":52031,"city_pref_name":"\u4eac\u90fd\u5e9c","city_name":"\u76f8\u697d\u90e1\u548c\u675f\u753a","city_pref":52,"city_detail":"\u5712","zip_code":"6191201"},"70":{"city_order":31,"city_id":52031,"city_pref_name":"\u4eac\u90fd\u5e9c","city_name":"\u76f8\u697d\u90e1\u548c\u675f\u753a","city_pref":52,"city_detail":"\u539f\u5c71","zip_code":"6191202"},"71":{"city_order":31,"city_id":52031,"city_pref_name":"\u4eac\u90fd\u5e9c","city_name":"\u76f8\u697d\u90e1\u548c\u675f\u753a","city_pref":52,"city_detail":"\u6e6f\u8239","zip_code":"6191203"},"72":{"city_order":31,"city_id":52031,"city_pref_name":"\u4eac\u90fd\u5e9c","city_name":"\u76f8\u697d\u90e1\u548c\u675f\u753a","city_pref":52,"city_detail":"\u9580\u524d","zip_code":"6191204"},"73":{"city_order":31,"city_id":52031,"city_pref_name":"\u4eac\u90fd\u5e9c","city_name":"\u76f8\u697d\u90e1\u548c\u675f\u753a","city_pref":52,"city_detail":"\u4e2d","zip_code":"6191205"},"74":{"city_order":31,"city_id":52031,"city_pref_name":"\u4eac\u90fd\u5e9c","city_name":"\u76f8\u697d\u90e1\u548c\u675f\u753a","city_pref":52,"city_detail":"\u5225\u6240","zip_code":"6191211"},"75":{"city_order":31,"city_id":52031,"city_pref_name":"\u4eac\u90fd\u5e9c","city_name":"\u76f8\u697d\u90e1\u548c\u675f\u753a","city_pref":52,"city_detail":"\u91dc\u585a","zip_code":"6191212"},"76":{"city_order":31,"city_id":52031,"city_pref_name":"\u4eac\u90fd\u5e9c","city_name":"\u76f8\u697d\u90e1\u548c\u675f\u753a","city_pref":52,"city_detail":"\u5357","zip_code":"6191213"},"77":{"city_order":31,"city_id":52031,"city_pref_name":"\u4eac\u90fd\u5e9c","city_name":"\u76f8\u697d\u90e1\u548c\u675f\u753a","city_pref":52,"city_detail":"\u77f3\u5bfa","zip_code":"6191221"},"78":{"city_order":31,"city_id":52031,"city_pref_name":"\u4eac\u90fd\u5e9c","city_name":"\u76f8\u697d\u90e1\u548c\u675f\u753a","city_pref":52,"city_detail":"\u767d\u6816","zip_code":"6191222"},"79":{"city_order":31,"city_id":52031,"city_pref_name":"\u4eac\u90fd\u5e9c","city_name":"\u76f8\u697d\u90e1\u548c\u675f\u753a","city_pref":52,"city_detail":"\u6763\u7530","zip_code":"6191223"},"80":{"city_order":31,"city_id":52031,"city_pref_name":"\u4eac\u90fd\u5e9c","city_name":"\u76f8\u697d\u90e1\u548c\u675f\u753a","city_pref":52,"city_detail":"\u6728\u5c4b","zip_code":"6191224"},"81":{"city_order":31,"city_id":52031,"city_pref_name":"\u4eac\u90fd\u5e9c","city_name":"\u76f8\u697d\u90e1\u548c\u675f\u753a","city_pref":52,"city_detail":"\u64b0\u539f","zip_code":"6191225"},"82":{"city_order":31,"city_id":52031,"city_pref_name":"\u4eac\u90fd\u5e9c","city_name":"\u76f8\u697d\u90e1\u548c\u675f\u753a","city_pref":52,"city_detail":"\u4e0b\u5cf6","zip_code":"6191226"},"83":{"city_order":30,"city_id":52030,"city_pref_name":"\u4eac\u90fd\u5e9c","city_name":"\u76f8\u697d\u90e1\u7b20\u7f6e\u753a","city_pref":52,"city_detail":"","zip_code":"6191300"},"84":{"city_order":30,"city_id":52030,"city_pref_name":"\u4eac\u90fd\u5e9c","city_name":"\u76f8\u697d\u90e1\u7b20\u7f6e\u753a","city_pref":52,"city_detail":"\u6709\u5e02","zip_code":"6191301"},"85":{"city_order":30,"city_id":52030,"city_pref_name":"\u4eac\u90fd\u5e9c","city_name":"\u76f8\u697d\u90e1\u7b20\u7f6e\u753a","city_pref":52,"city_detail":"\u98db\u9ce5\u8def","zip_code":"6191302"},"86":{"city_order":30,"city_id":52030,"city_pref_name":"\u4eac\u90fd\u5e9c","city_name":"\u76f8\u697d\u90e1\u7b20\u7f6e\u753a","city_pref":52,"city_detail":"\u7b20\u7f6e","zip_code":"6191303"},"87":{"city_order":30,"city_id":52030,"city_pref_name":"\u4eac\u90fd\u5e9c","city_name":"\u76f8\u697d\u90e1\u7b20\u7f6e\u753a","city_pref":52,"city_detail":"\u5207\u5c71","zip_code":"6191304"},"88":{"city_order":33,"city_id":52033,"city_pref_name":"\u4eac\u90fd\u5e9c","city_name":"\u76f8\u697d\u90e1\u5357\u5c71\u57ce\u6751","city_pref":52,"city_detail":"","zip_code":"6191400"},"89":{"city_order":33,"city_id":52033,"city_pref_name":"\u4eac\u90fd\u5e9c","city_name":"\u76f8\u697d\u90e1\u5357\u5c71\u57ce\u6751","city_pref":52,"city_detail":"\u7ae5\u4ed9\u623f","zip_code":"6191401"},"90":{"city_order":33,"city_id":52033,"city_pref_name":"\u4eac\u90fd\u5e9c","city_name":"\u76f8\u697d\u90e1\u5357\u5c71\u57ce\u6751","city_pref":52,"city_detail":"\u91ce\u6bbf","zip_code":"6191402"},"91":{"city_order":33,"city_id":52033,"city_pref_name":"\u4eac\u90fd\u5e9c","city_name":"\u76f8\u697d\u90e1\u5357\u5c71\u57ce\u6751","city_pref":52,"city_detail":"\u5317\u5927\u6cb3\u539f","zip_code":"6191411"},"92":{"city_order":33,"city_id":52033,"city_pref_name":"\u4eac\u90fd\u5e9c","city_name":"\u76f8\u697d\u90e1\u5357\u5c71\u57ce\u6751","city_pref":52,"city_detail":"\u5357\u5927\u6cb3\u539f","zip_code":"6191412"},"93":{"city_order":33,"city_id":52033,"city_pref_name":"\u4eac\u90fd\u5e9c","city_name":"\u76f8\u697d\u90e1\u5357\u5c71\u57ce\u6751","city_pref":52,"city_detail":"\u7530\u5c71","zip_code":"6191421"},"94":{"city_order":33,"city_id":52033,"city_pref_name":"\u4eac\u90fd\u5e9c","city_name":"\u76f8\u697d\u90e1\u5357\u5c71\u57ce\u6751","city_pref":52,"city_detail":"\u9ad8\u5c3e","zip_code":"6191422"},"city_list":{"52001":"\u4eac\u90fd\u5e02\u5317\u533a","52002":"\u4eac\u90fd\u5e02\u4e0a\u4eac\u533a","52003":"\u4eac\u90fd\u5e02\u5de6\u4eac\u533a","52004":"\u4eac\u90fd\u5e02\u4e2d\u4eac\u533a","52005":"\u4eac\u90fd\u5e02\u6771\u5c71\u533a","52006":"\u4eac\u90fd\u5e02\u4e0b\u4eac\u533a","52007":"\u4eac\u90fd\u5e02\u5357\u533a","52008":"\u4eac\u90fd\u5e02\u53f3\u4eac\u533a","52009":"\u4eac\u90fd\u5e02\u4f0f\u898b\u533a","52010":"\u4eac\u90fd\u5e02\u5c71\u79d1\u533a","52011":"\u4eac\u90fd\u5e02\u897f\u4eac\u533a","52012":"\u798f\u77e5\u5c71\u5e02","52013":"\u821e\u9db4\u5e02","52014":"\u7dbe\u90e8\u5e02","52015":"\u5b87\u6cbb\u5e02","52016":"\u5bae\u6d25\u5e02","52017":"\u4e80\u5ca1\u5e02","52018":"\u57ce\u967d\u5e02","52019":"\u5411\u65e5\u5e02","52020":"\u9577\u5ca1\u4eac\u5e02","52021":"\u516b\u5e61\u5e02","52022":"\u4eac\u7530\u8fba\u5e02","52023":"\u4eac\u4e39\u5f8c\u5e02","52024":"\u5357\u4e39\u5e02","52025":"\u6728\u6d25\u5ddd\u5e02","52026":"\u4e59\u8a13\u90e1\u5927\u5c71\u5d0e\u753a","52027":"\u4e45\u4e16\u90e1\u4e45\u5fa1\u5c71\u753a","52028":"\u7db4\u559c\u90e1\u4e95\u624b\u753a","52029":"\u7db4\u559c\u90e1\u5b87\u6cbb\u7530\u539f\u753a","52030":"\u76f8\u697d\u90e1\u7b20\u7f6e\u753a","52031":"\u76f8\u697d\u90e1\u548c\u675f\u753a","52032":"\u76f8\u697d\u90e1\u7cbe\u83ef\u753a","52033":"\u76f8\u697d\u90e1\u5357\u5c71\u57ce\u6751","52034":"\u8239\u4e95\u90e1\u4eac\u4e39\u6ce2\u753a","52035":"\u4e0e\u8b1d\u90e1\u4f0a\u6839\u753a","52036":"\u4e0e\u8b1d\u90e1\u4e0e\u8b1d\u91ce\u753a","52999":"\uff08\u65e7\u4f4f\u6240\uff09"}}