{"0":{"city_order":1,"city_id":71001,"city_pref_name":"\u5fb3\u5cf6\u770c","city_name":"\u5fb3\u5cf6\u5e02","city_pref":71,"city_detail":"","zip_code":"7700000"},"1":{"city_order":1,"city_id":71001,"city_pref_name":"\u5fb3\u5cf6\u770c","city_name":"\u5fb3\u5cf6\u5e02","city_pref":71,"city_detail":"\u6625\u65e5\u753a","zip_code":"7700001"},"2":{"city_order":1,"city_id":71001,"city_pref_name":"\u5fb3\u5cf6\u770c","city_name":"\u5fb3\u5cf6\u5e02","city_pref":71,"city_detail":"\u6625\u65e5","zip_code":"7700002"},"3":{"city_order":1,"city_id":71001,"city_pref_name":"\u5fb3\u5cf6\u770c","city_name":"\u5fb3\u5cf6\u5e02","city_pref":71,"city_detail":"\u5317\u7530\u5bae","zip_code":"7700003"},"4":{"city_order":1,"city_id":71001,"city_pref_name":"\u5fb3\u5cf6\u770c","city_name":"\u5fb3\u5cf6\u5e02","city_pref":71,"city_detail":"\u5357\u7530\u5bae","zip_code":"7700004"},"5":{"city_order":1,"city_id":71001,"city_pref_name":"\u5fb3\u5cf6\u770c","city_name":"\u5fb3\u5cf6\u5e02","city_pref":71,"city_detail":"\u5357\u77e2\u4e09\u753a","zip_code":"7700005"},"6":{"city_order":1,"city_id":71001,"city_pref_name":"\u5fb3\u5cf6\u770c","city_name":"\u5fb3\u5cf6\u5e02","city_pref":71,"city_detail":"\u5317\u77e2\u4e09\u753a","zip_code":"7700006"},"7":{"city_order":1,"city_id":71001,"city_pref_name":"\u5fb3\u5cf6\u770c","city_name":"\u5fb3\u5cf6\u5e02","city_pref":71,"city_detail":"\u5317\u4f50\u53e4\u4e00\u756a\u753a","zip_code":"7700011"},"8":{"city_order":1,"city_id":71001,"city_pref_name":"\u5fb3\u5cf6\u770c","city_name":"\u5fb3\u5cf6\u5e02","city_pref":71,"city_detail":"\u5317\u4f50\u53e4\u4e8c\u756a\u753a","zip_code":"7700012"},"9":{"city_order":1,"city_id":71001,"city_pref_name":"\u5fb3\u5cf6\u770c","city_name":"\u5fb3\u5cf6\u5e02","city_pref":71,"city_detail":"\u4f50\u53e4\u4e00\u756a\u753a","zip_code":"7700021"},"10":{"city_order":1,"city_id":71001,"city_pref_name":"\u5fb3\u5cf6\u770c","city_name":"\u5fb3\u5cf6\u5e02","city_pref":71,"city_detail":"\u4f50\u53e4\u4e8c\u756a\u753a","zip_code":"7700022"},"11":{"city_order":1,"city_id":71001,"city_pref_name":"\u5fb3\u5cf6\u770c","city_name":"\u5fb3\u5cf6\u5e02","city_pref":71,"city_detail":"\u4f50\u53e4\u4e09\u756a\u753a","zip_code":"7700023"},"12":{"city_order":1,"city_id":71001,"city_pref_name":"\u5fb3\u5cf6\u770c","city_name":"\u5fb3\u5cf6\u5e02","city_pref":71,"city_detail":"\u4f50\u53e4\u56db\u756a\u753a","zip_code":"7700024"},"13":{"city_order":1,"city_id":71001,"city_pref_name":"\u5fb3\u5cf6\u770c","city_name":"\u5fb3\u5cf6\u5e02","city_pref":71,"city_detail":"\u4f50\u53e4\u4e94\u756a\u753a","zip_code":"7700025"},"14":{"city_order":1,"city_id":71001,"city_pref_name":"\u5fb3\u5cf6\u770c","city_name":"\u5fb3\u5cf6\u5e02","city_pref":71,"city_detail":"\u4f50\u53e4\u516d\u756a\u753a","zip_code":"7700026"},"15":{"city_order":1,"city_id":71001,"city_pref_name":"\u5fb3\u5cf6\u770c","city_name":"\u5fb3\u5cf6\u5e02","city_pref":71,"city_detail":"\u4f50\u53e4\u4e03\u756a\u753a","zip_code":"7700027"},"16":{"city_order":1,"city_id":71001,"city_pref_name":"\u5fb3\u5cf6\u770c","city_name":"\u5fb3\u5cf6\u5e02","city_pref":71,"city_detail":"\u4f50\u53e4\u516b\u756a\u753a","zip_code":"7700028"},"17":{"city_order":1,"city_id":71001,"city_pref_name":"\u5fb3\u5cf6\u770c","city_name":"\u5fb3\u5cf6\u5e02","city_pref":71,"city_detail":"\u5357\u4f50\u53e4\u4e00\u756a\u753a","zip_code":"7700031"},"18":{"city_order":1,"city_id":71001,"city_pref_name":"\u5fb3\u5cf6\u770c","city_name":"\u5fb3\u5cf6\u5e02","city_pref":71,"city_detail":"\u5357\u4f50\u53e4\u4e8c\u756a\u753a","zip_code":"7700032"},"19":{"city_order":1,"city_id":71001,"city_pref_name":"\u5fb3\u5cf6\u770c","city_name":"\u5fb3\u5cf6\u5e02","city_pref":71,"city_detail":"\u5357\u4f50\u53e4\u4e09\u756a\u753a","zip_code":"7700033"},"20":{"city_order":1,"city_id":71001,"city_pref_name":"\u5fb3\u5cf6\u770c","city_name":"\u5fb3\u5cf6\u5e02","city_pref":71,"city_detail":"\u5357\u4f50\u53e4\u56db\u756a\u753a","zip_code":"7700034"},"21":{"city_order":1,"city_id":71001,"city_pref_name":"\u5fb3\u5cf6\u770c","city_name":"\u5fb3\u5cf6\u5e02","city_pref":71,"city_detail":"\u5357\u4f50\u53e4\u4e94\u756a\u753a","zip_code":"7700035"},"22":{"city_order":1,"city_id":71001,"city_pref_name":"\u5fb3\u5cf6\u770c","city_name":"\u5fb3\u5cf6\u5e02","city_pref":71,"city_detail":"\u5357\u4f50\u53e4\u516d\u756a\u753a","zip_code":"7700036"},"23":{"city_order":1,"city_id":71001,"city_pref_name":"\u5fb3\u5cf6\u770c","city_name":"\u5fb3\u5cf6\u5e02","city_pref":71,"city_detail":"\u5357\u4f50\u53e4\u4e03\u756a\u753a","zip_code":"7700037"},"24":{"city_order":1,"city_id":71001,"city_pref_name":"\u5fb3\u5cf6\u770c","city_name":"\u5fb3\u5cf6\u5e02","city_pref":71,"city_detail":"\u5357\u4f50\u53e4\u516b\u756a\u753a","zip_code":"7700038"},"25":{"city_order":1,"city_id":71001,"city_pref_name":"\u5fb3\u5cf6\u770c","city_name":"\u5fb3\u5cf6\u5e02","city_pref":71,"city_detail":"\u4f50\u53e4\u5c71\u753a","zip_code":"7700039"},"26":{"city_order":1,"city_id":71001,"city_pref_name":"\u5fb3\u5cf6\u770c","city_name":"\u5fb3\u5cf6\u5e02","city_pref":71,"city_detail":"\u8535\u672c\u5143\u753a","zip_code":"7700041"},"27":{"city_order":1,"city_id":71001,"city_pref_name":"\u5fb3\u5cf6\u770c","city_name":"\u5fb3\u5cf6\u5e02","city_pref":71,"city_detail":"\u8535\u672c\u753a","zip_code":"7700042"},"28":{"city_order":1,"city_id":71001,"city_pref_name":"\u5fb3\u5cf6\u770c","city_name":"\u5fb3\u5cf6\u5e02","city_pref":71,"city_detail":"\u5357\u8535\u672c\u753a","zip_code":"7700043"},"29":{"city_order":1,"city_id":71001,"city_pref_name":"\u5fb3\u5cf6\u770c","city_name":"\u5fb3\u5cf6\u5e02","city_pref":71,"city_detail":"\u5e84\u753a","zip_code":"7700044"},"30":{"city_order":1,"city_id":71001,"city_pref_name":"\u5fb3\u5cf6\u770c","city_name":"\u5fb3\u5cf6\u5e02","city_pref":71,"city_detail":"\u5357\u5e84\u753a","zip_code":"7700045"},"31":{"city_order":1,"city_id":71001,"city_pref_name":"\u5fb3\u5cf6\u770c","city_name":"\u5fb3\u5cf6\u5e02","city_pref":71,"city_detail":"\u9b8e\u55b0\u753a","zip_code":"7700046"},"32":{"city_order":1,"city_id":71001,"city_pref_name":"\u5fb3\u5cf6\u770c","city_name":"\u5fb3\u5cf6\u5e02","city_pref":71,"city_detail":"\u540d\u6771\u753a","zip_code":"7700047"},"33":{"city_order":1,"city_id":71001,"city_pref_name":"\u5fb3\u5cf6\u770c","city_name":"\u5fb3\u5cf6\u5e02","city_pref":71,"city_detail":"\u52a0\u8302\u540d\u753a","zip_code":"7700048"},"34":{"city_order":1,"city_id":71001,"city_pref_name":"\u5fb3\u5cf6\u770c","city_name":"\u5fb3\u5cf6\u5e02","city_pref":71,"city_detail":"\u5317\u5cf6\u7530\u753a","zip_code":"7700051"},"35":{"city_order":1,"city_id":71001,"city_pref_name":"\u5fb3\u5cf6\u770c","city_name":"\u5fb3\u5cf6\u5e02","city_pref":71,"city_detail":"\u4e2d\u5cf6\u7530\u753a","zip_code":"7700052"},"36":{"city_order":1,"city_id":71001,"city_pref_name":"\u5fb3\u5cf6\u770c","city_name":"\u5fb3\u5cf6\u5e02","city_pref":71,"city_detail":"\u5357\u5cf6\u7530\u753a","zip_code":"7700053"},"37":{"city_order":1,"city_id":71001,"city_pref_name":"\u5fb3\u5cf6\u770c","city_name":"\u5fb3\u5cf6\u5e02","city_pref":71,"city_detail":"\u4e0d\u52d5\u5317\u753a","zip_code":"7700061"},"38":{"city_order":1,"city_id":71001,"city_pref_name":"\u5fb3\u5cf6\u770c","city_name":"\u5fb3\u5cf6\u5e02","city_pref":71,"city_detail":"\u4e0d\u52d5\u6771\u753a","zip_code":"7700062"},"39":{"city_order":1,"city_id":71001,"city_pref_name":"\u5fb3\u5cf6\u770c","city_name":"\u5fb3\u5cf6\u5e02","city_pref":71,"city_detail":"\u4e0d\u52d5\u672c\u753a","zip_code":"7700063"},"40":{"city_order":1,"city_id":71001,"city_pref_name":"\u5fb3\u5cf6\u770c","city_name":"\u5fb3\u5cf6\u5e02","city_pref":71,"city_detail":"\u4e0d\u52d5\u897f\u753a","zip_code":"7700064"},"41":{"city_order":1,"city_id":71001,"city_pref_name":"\u5fb3\u5cf6\u770c","city_name":"\u5fb3\u5cf6\u5e02","city_pref":71,"city_detail":"\u4e0a\u52a9\u4efb\u753a","zip_code":"7700801"},"42":{"city_order":1,"city_id":71001,"city_pref_name":"\u5fb3\u5cf6\u770c","city_name":"\u5fb3\u5cf6\u5e02","city_pref":71,"city_detail":"\u5409\u91ce\u672c\u753a","zip_code":"7700802"},"43":{"city_order":1,"city_id":71001,"city_pref_name":"\u5fb3\u5cf6\u770c","city_name":"\u5fb3\u5cf6\u5e02","city_pref":71,"city_detail":"\u4e0a\u5409\u91ce\u753a","zip_code":"7700803"},"44":{"city_order":1,"city_id":71001,"city_pref_name":"\u5fb3\u5cf6\u770c","city_name":"\u5fb3\u5cf6\u5e02","city_pref":71,"city_detail":"\u4e2d\u5409\u91ce\u753a","zip_code":"7700804"},"45":{"city_order":1,"city_id":71001,"city_pref_name":"\u5fb3\u5cf6\u770c","city_name":"\u5fb3\u5cf6\u5e02","city_pref":71,"city_detail":"\u4e0b\u52a9\u4efb\u753a","zip_code":"7700805"},"46":{"city_order":1,"city_id":71001,"city_pref_name":"\u5fb3\u5cf6\u770c","city_name":"\u5fb3\u5cf6\u5e02","city_pref":71,"city_detail":"\u5317\u524d\u5ddd\u753a","zip_code":"7700806"},"47":{"city_order":1,"city_id":71001,"city_pref_name":"\u5fb3\u5cf6\u770c","city_name":"\u5fb3\u5cf6\u5e02","city_pref":71,"city_detail":"\u4e2d\u524d\u5ddd\u753a","zip_code":"7700807"},"48":{"city_order":1,"city_id":71001,"city_pref_name":"\u5fb3\u5cf6\u770c","city_name":"\u5fb3\u5cf6\u5e02","city_pref":71,"city_detail":"\u5357\u524d\u5ddd\u753a","zip_code":"7700808"},"49":{"city_order":1,"city_id":71001,"city_pref_name":"\u5fb3\u5cf6\u770c","city_name":"\u5fb3\u5cf6\u5e02","city_pref":71,"city_detail":"\u6771\u5409\u91ce\u753a","zip_code":"7700811"},"50":{"city_order":1,"city_id":71001,"city_pref_name":"\u5fb3\u5cf6\u770c","city_name":"\u5fb3\u5cf6\u5e02","city_pref":71,"city_detail":"\u5317\u5e38\u4e09\u5cf6\u753a","zip_code":"7700812"},"51":{"city_order":1,"city_id":71001,"city_pref_name":"\u5fb3\u5cf6\u770c","city_name":"\u5fb3\u5cf6\u5e02","city_pref":71,"city_detail":"\u4e2d\u5e38\u4e09\u5cf6\u753a","zip_code":"7700813"},"52":{"city_order":1,"city_id":71001,"city_pref_name":"\u5fb3\u5cf6\u770c","city_name":"\u5fb3\u5cf6\u5e02","city_pref":71,"city_detail":"\u5357\u5e38\u4e09\u5cf6\u753a","zip_code":"7700814"},"53":{"city_order":1,"city_id":71001,"city_pref_name":"\u5fb3\u5cf6\u770c","city_name":"\u5fb3\u5cf6\u5e02","city_pref":71,"city_detail":"\u52a9\u4efb\u6a4b","zip_code":"7700815"},"54":{"city_order":1,"city_id":71001,"city_pref_name":"\u5fb3\u5cf6\u770c","city_name":"\u5fb3\u5cf6\u5e02","city_pref":71,"city_detail":"\u52a9\u4efb\u672c\u753a","zip_code":"7700816"},"55":{"city_order":1,"city_id":71001,"city_pref_name":"\u5fb3\u5cf6\u770c","city_name":"\u5fb3\u5cf6\u5e02","city_pref":71,"city_detail":"\u5317\u51fa\u6765\u5cf6\u753a","zip_code":"7700821"},"56":{"city_order":1,"city_id":71001,"city_pref_name":"\u5fb3\u5cf6\u770c","city_name":"\u5fb3\u5cf6\u5e02","city_pref":71,"city_detail":"\u6771\u51fa\u6765\u5cf6\u753a","zip_code":"7700822"},"57":{"city_order":1,"city_id":71001,"city_pref_name":"\u5fb3\u5cf6\u770c","city_name":"\u5fb3\u5cf6\u5e02","city_pref":71,"city_detail":"\u51fa\u6765\u5cf6\u672c\u753a","zip_code":"7700823"},"58":{"city_order":1,"city_id":71001,"city_pref_name":"\u5fb3\u5cf6\u770c","city_name":"\u5fb3\u5cf6\u5e02","city_pref":71,"city_detail":"\u5357\u51fa\u6765\u5cf6\u753a","zip_code":"7700824"},"59":{"city_order":1,"city_id":71001,"city_pref_name":"\u5fb3\u5cf6\u770c","city_name":"\u5fb3\u5cf6\u5e02","city_pref":71,"city_detail":"\u5bfa\u5cf6\u672c\u753a\u897f","zip_code":"7700831"},"60":{"city_order":1,"city_id":71001,"city_pref_name":"\u5fb3\u5cf6\u770c","city_name":"\u5fb3\u5cf6\u5e02","city_pref":71,"city_detail":"\u5bfa\u5cf6\u672c\u753a\u6771","zip_code":"7700832"},"61":{"city_order":1,"city_id":71001,"city_pref_name":"\u5fb3\u5cf6\u770c","city_name":"\u5fb3\u5cf6\u5e02","city_pref":71,"city_detail":"\u4e00\u756a\u753a","zip_code":"7700833"},"62":{"city_order":1,"city_id":71001,"city_pref_name":"\u5fb3\u5cf6\u770c","city_name":"\u5fb3\u5cf6\u5e02","city_pref":71,"city_detail":"\u5143\u753a","zip_code":"7700834"},"63":{"city_order":1,"city_id":71001,"city_pref_name":"\u5fb3\u5cf6\u770c","city_name":"\u5fb3\u5cf6\u5e02","city_pref":71,"city_detail":"\u85cd\u5834\u753a","zip_code":"7700835"},"64":{"city_order":1,"city_id":71001,"city_pref_name":"\u5fb3\u5cf6\u770c","city_name":"\u5fb3\u5cf6\u5e02","city_pref":71,"city_detail":"\u516b\u767e\u5c4b\u753a","zip_code":"7700841"},"65":{"city_order":1,"city_id":71001,"city_pref_name":"\u5fb3\u5cf6\u770c","city_name":"\u5fb3\u5cf6\u5e02","city_pref":71,"city_detail":"\u901a\u753a","zip_code":"7700842"},"66":{"city_order":1,"city_id":71001,"city_pref_name":"\u5fb3\u5cf6\u770c","city_name":"\u5fb3\u5cf6\u5e02","city_pref":71,"city_detail":"\u4e21\u56fd\u672c\u753a","zip_code":"7700843"},"67":{"city_order":1,"city_id":71001,"city_pref_name":"\u5fb3\u5cf6\u770c","city_name":"\u5fb3\u5cf6\u5e02","city_pref":71,"city_detail":"\u4e2d\u901a\u753a","zip_code":"7700844"},"68":{"city_order":1,"city_id":71001,"city_pref_name":"\u5fb3\u5cf6\u770c","city_name":"\u5fb3\u5cf6\u5e02","city_pref":71,"city_detail":"\u65b0\u5185\u753a","zip_code":"7700845"},"69":{"city_order":1,"city_id":71001,"city_pref_name":"\u5fb3\u5cf6\u770c","city_name":"\u5fb3\u5cf6\u5e02","city_pref":71,"city_detail":"\u5357\u5185\u753a","zip_code":"7700846"},"70":{"city_order":1,"city_id":71001,"city_pref_name":"\u5fb3\u5cf6\u770c","city_name":"\u5fb3\u5cf6\u5e02","city_pref":71,"city_detail":"\u5e78\u753a","zip_code":"7700847"},"71":{"city_order":1,"city_id":71001,"city_pref_name":"\u5fb3\u5cf6\u770c","city_name":"\u5fb3\u5cf6\u5e02","city_pref":71,"city_detail":"\u5fb3\u5cf6\u753a\u57ce\u5185","zip_code":"7700851"},"72":{"city_order":1,"city_id":71001,"city_pref_name":"\u5fb3\u5cf6\u770c","city_name":"\u5fb3\u5cf6\u5e02","city_pref":71,"city_detail":"\u5fb3\u5cf6\u753a","zip_code":"7700852"},"73":{"city_order":1,"city_id":71001,"city_pref_name":"\u5fb3\u5cf6\u770c","city_name":"\u5fb3\u5cf6\u5e02","city_pref":71,"city_detail":"\u4e2d\u5fb3\u5cf6\u753a","zip_code":"7700853"},"74":{"city_order":1,"city_id":71001,"city_pref_name":"\u5fb3\u5cf6\u770c","city_name":"\u5fb3\u5cf6\u5e02","city_pref":71,"city_detail":"\u5fb3\u5cf6\u672c\u753a","zip_code":"7700854"},"75":{"city_order":1,"city_id":71001,"city_pref_name":"\u5fb3\u5cf6\u770c","city_name":"\u5fb3\u5cf6\u5e02","city_pref":71,"city_detail":"\u65b0\u8535\u753a","zip_code":"7700855"},"76":{"city_order":1,"city_id":71001,"city_pref_name":"\u5fb3\u5cf6\u770c","city_name":"\u5fb3\u5cf6\u5e02","city_pref":71,"city_detail":"\u4e2d\u6d32\u753a","zip_code":"7700856"},"77":{"city_order":1,"city_id":71001,"city_pref_name":"\u5fb3\u5cf6\u770c","city_name":"\u5fb3\u5cf6\u5e02","city_pref":71,"city_detail":"\u4f4f\u5409","zip_code":"7700861"},"78":{"city_order":1,"city_id":71001,"city_pref_name":"\u5fb3\u5cf6\u770c","city_name":"\u5fb3\u5cf6\u5e02","city_pref":71,"city_detail":"\u57ce\u6771\u753a","zip_code":"7700862"},"79":{"city_order":1,"city_id":71001,"city_pref_name":"\u5fb3\u5cf6\u770c","city_name":"\u5fb3\u5cf6\u5e02","city_pref":71,"city_detail":"\u5b89\u5b85","zip_code":"7700863"},"80":{"city_order":1,"city_id":71001,"city_pref_name":"\u5fb3\u5cf6\u770c","city_name":"\u5fb3\u5cf6\u5e02","city_pref":71,"city_detail":"\u5927\u548c\u753a","zip_code":"7700864"},"81":{"city_order":1,"city_id":71001,"city_pref_name":"\u5fb3\u5cf6\u770c","city_name":"\u5fb3\u5cf6\u5e02","city_pref":71,"city_detail":"\u5357\u672b\u5e83\u753a","zip_code":"7700865"},"82":{"city_order":1,"city_id":71001,"city_pref_name":"\u5fb3\u5cf6\u770c","city_name":"\u5fb3\u5cf6\u5e02","city_pref":71,"city_detail":"\u672b\u5e83","zip_code":"7700866"},"83":{"city_order":1,"city_id":71001,"city_pref_name":"\u5fb3\u5cf6\u770c","city_name":"\u5fb3\u5cf6\u5e02","city_pref":71,"city_detail":"\u65b0\u5357\u798f\u5cf6","zip_code":"7700867"},"84":{"city_order":1,"city_id":71001,"city_pref_name":"\u5fb3\u5cf6\u770c","city_name":"\u5fb3\u5cf6\u5e02","city_pref":71,"city_detail":"\u798f\u5cf6","zip_code":"7700868"},"85":{"city_order":1,"city_id":71001,"city_pref_name":"\u5fb3\u5cf6\u770c","city_name":"\u5fb3\u5cf6\u5e02","city_pref":71,"city_detail":"\u91d1\u6ca2","zip_code":"7700871"},"86":{"city_order":1,"city_id":71001,"city_pref_name":"\u5fb3\u5cf6\u770c","city_name":"\u5fb3\u5cf6\u5e02","city_pref":71,"city_detail":"\u5317\u6c96\u6d32","zip_code":"7700872"},"87":{"city_order":1,"city_id":71001,"city_pref_name":"\u5fb3\u5cf6\u770c","city_name":"\u5fb3\u5cf6\u5e02","city_pref":71,"city_detail":"\u6771\u6c96\u6d32","zip_code":"7700873"},"88":{"city_order":1,"city_id":71001,"city_pref_name":"\u5fb3\u5cf6\u770c","city_name":"\u5fb3\u5cf6\u5e02","city_pref":71,"city_detail":"\u5357\u6c96\u6d32","zip_code":"7700874"},"89":{"city_order":1,"city_id":71001,"city_pref_name":"\u5fb3\u5cf6\u770c","city_name":"\u5fb3\u5cf6\u5e02","city_pref":71,"city_detail":"\u897f\u8239\u5834\u753a","zip_code":"7700901"},"90":{"city_order":1,"city_id":71001,"city_pref_name":"\u5fb3\u5cf6\u770c","city_name":"\u5fb3\u5cf6\u5e02","city_pref":71,"city_detail":"\u897f\u65b0\u753a","zip_code":"7700902"},"91":{"city_order":1,"city_id":71001,"city_pref_name":"\u5fb3\u5cf6\u770c","city_name":"\u5fb3\u5cf6\u5e02","city_pref":71,"city_detail":"\u897f\u5927\u5de5\u753a","zip_code":"7700903"},"92":{"city_order":1,"city_id":71001,"city_pref_name":"\u5fb3\u5cf6\u770c","city_name":"\u5fb3\u5cf6\u5e02","city_pref":71,"city_detail":"\u65b0\u753a\u6a4b","zip_code":"7700904"},"93":{"city_order":1,"city_id":71001,"city_pref_name":"\u5fb3\u5cf6\u770c","city_name":"\u5fb3\u5cf6\u5e02","city_pref":71,"city_detail":"\u6771\u5927\u5de5\u753a","zip_code":"7700905"},"94":{"city_order":1,"city_id":71001,"city_pref_name":"\u5fb3\u5cf6\u770c","city_name":"\u5fb3\u5cf6\u5e02","city_pref":71,"city_detail":"\u6771\u5c71\u624b\u753a","zip_code":"7700906"},"95":{"city_order":1,"city_id":71001,"city_pref_name":"\u5fb3\u5cf6\u770c","city_name":"\u5fb3\u5cf6\u5e02","city_pref":71,"city_detail":"\u897f\u5c71\u624b\u753a","zip_code":"7700907"},"96":{"city_order":1,"city_id":71001,"city_pref_name":"\u5fb3\u5cf6\u770c","city_name":"\u5fb3\u5cf6\u5e02","city_pref":71,"city_detail":"\u7709\u5c71\u753a","zip_code":"7700908"},"97":{"city_order":1,"city_id":71001,"city_pref_name":"\u5fb3\u5cf6\u770c","city_name":"\u5fb3\u5cf6\u5e02","city_pref":71,"city_detail":"\u5bfa\u753a","zip_code":"7700909"},"98":{"city_order":1,"city_id":71001,"city_pref_name":"\u5fb3\u5cf6\u770c","city_name":"\u5fb3\u5cf6\u5e02","city_pref":71,"city_detail":"\u6771\u8239\u5834\u753a","zip_code":"7700911"},"99":{"city_order":1,"city_id":71001,"city_pref_name":"\u5fb3\u5cf6\u770c","city_name":"\u5fb3\u5cf6\u5e02","city_pref":71,"city_detail":"\u6771\u65b0\u753a","zip_code":"7700912"},"100":{"city_order":1,"city_id":71001,"city_pref_name":"\u5fb3\u5cf6\u770c","city_name":"\u5fb3\u5cf6\u5e02","city_pref":71,"city_detail":"\u5357\u65b0\u753a","zip_code":"7700913"},"101":{"city_order":1,"city_id":71001,"city_pref_name":"\u5fb3\u5cf6\u770c","city_name":"\u5fb3\u5cf6\u5e02","city_pref":71,"city_detail":"\u7c60\u5c4b\u753a","zip_code":"7700914"},"102":{"city_order":1,"city_id":71001,"city_pref_name":"\u5fb3\u5cf6\u770c","city_name":"\u5fb3\u5cf6\u5e02","city_pref":71,"city_detail":"\u5bcc\u7530\u753a","zip_code":"7700915"},"103":{"city_order":1,"city_id":71001,"city_pref_name":"\u5fb3\u5cf6\u770c","city_name":"\u5fb3\u5cf6\u5e02","city_pref":71,"city_detail":"\u9280\u5ea7","zip_code":"7700916"},"104":{"city_order":1,"city_id":71001,"city_pref_name":"\u5fb3\u5cf6\u770c","city_name":"\u5fb3\u5cf6\u5e02","city_pref":71,"city_detail":"\u4e21\u56fd\u6a4b","zip_code":"7700917"},"105":{"city_order":1,"city_id":71001,"city_pref_name":"\u5fb3\u5cf6\u770c","city_name":"\u5fb3\u5cf6\u5e02","city_pref":71,"city_detail":"\u7d3a\u5c4b\u753a","zip_code":"7700918"},"106":{"city_order":1,"city_id":71001,"city_pref_name":"\u5fb3\u5cf6\u770c","city_name":"\u5fb3\u5cf6\u5e02","city_pref":71,"city_detail":"\u6804\u753a","zip_code":"7700921"},"107":{"city_order":1,"city_id":71001,"city_pref_name":"\u5fb3\u5cf6\u770c","city_name":"\u5fb3\u5cf6\u5e02","city_pref":71,"city_detail":"\u9df9\u5320\u753a","zip_code":"7700922"},"108":{"city_order":1,"city_id":71001,"city_pref_name":"\u5fb3\u5cf6\u770c","city_name":"\u5fb3\u5cf6\u5e02","city_pref":71,"city_detail":"\u5927\u9053","zip_code":"7700923"},"109":{"city_order":1,"city_id":71001,"city_pref_name":"\u5fb3\u5cf6\u770c","city_name":"\u5fb3\u5cf6\u5e02","city_pref":71,"city_detail":"\u5e5f\u753a","zip_code":"7700924"},"110":{"city_order":1,"city_id":71001,"city_pref_name":"\u5fb3\u5cf6\u770c","city_name":"\u5fb3\u5cf6\u5e02","city_pref":71,"city_detail":"\u5f13\u753a","zip_code":"7700925"},"111":{"city_order":1,"city_id":71001,"city_pref_name":"\u5fb3\u5cf6\u770c","city_name":"\u5fb3\u5cf6\u5e02","city_pref":71,"city_detail":"\u4f0a\u8cc0\u753a","zip_code":"7700926"},"112":{"city_order":1,"city_id":71001,"city_pref_name":"\u5fb3\u5cf6\u770c","city_name":"\u5fb3\u5cf6\u5e02","city_pref":71,"city_detail":"\u52e2\u898b\u753a","zip_code":"7700927"},"113":{"city_order":1,"city_id":71001,"city_pref_name":"\u5fb3\u5cf6\u770c","city_name":"\u5fb3\u5cf6\u5e02","city_pref":71,"city_detail":"\u4e8c\u8ed2\u5c4b\u753a","zip_code":"7700928"},"114":{"city_order":1,"city_id":71001,"city_pref_name":"\u5fb3\u5cf6\u770c","city_name":"\u5fb3\u5cf6\u5e02","city_pref":71,"city_detail":"\u897f\u5bcc\u7530\u753a","zip_code":"7700929"},"115":{"city_order":1,"city_id":71001,"city_pref_name":"\u5fb3\u5cf6\u770c","city_name":"\u5fb3\u5cf6\u5e02","city_pref":71,"city_detail":"\u5bcc\u7530\u6d5c","zip_code":"7700931"},"116":{"city_order":1,"city_id":71001,"city_pref_name":"\u5fb3\u5cf6\u770c","city_name":"\u5fb3\u5cf6\u5e02","city_pref":71,"city_detail":"\u4ef2\u4e4b\u753a","zip_code":"7700932"},"117":{"city_order":1,"city_id":71001,"city_pref_name":"\u5fb3\u5cf6\u770c","city_name":"\u5fb3\u5cf6\u5e02","city_pref":71,"city_detail":"\u5357\u4ef2\u4e4b\u753a","zip_code":"7700933"},"118":{"city_order":1,"city_id":71001,"city_pref_name":"\u5fb3\u5cf6\u770c","city_name":"\u5fb3\u5cf6\u5e02","city_pref":71,"city_detail":"\u79cb\u7530\u753a","zip_code":"7700934"},"119":{"city_order":1,"city_id":71001,"city_pref_name":"\u5fb3\u5cf6\u770c","city_name":"\u5fb3\u5cf6\u5e02","city_pref":71,"city_detail":"\u4f0a\u6708\u753a","zip_code":"7700935"},"120":{"city_order":1,"city_id":71001,"city_pref_name":"\u5fb3\u5cf6\u770c","city_name":"\u5fb3\u5cf6\u5e02","city_pref":71,"city_detail":"\u4e2d\u592e\u901a","zip_code":"7700936"},"121":{"city_order":1,"city_id":71001,"city_pref_name":"\u5fb3\u5cf6\u770c","city_name":"\u5fb3\u5cf6\u5e02","city_pref":71,"city_detail":"\u5bcc\u7530\u6a4b","zip_code":"7700937"},"122":{"city_order":1,"city_id":71001,"city_pref_name":"\u5fb3\u5cf6\u770c","city_name":"\u5fb3\u5cf6\u5e02","city_pref":71,"city_detail":"\u660e\u795e\u753a","zip_code":"7700938"},"123":{"city_order":1,"city_id":71001,"city_pref_name":"\u5fb3\u5cf6\u770c","city_name":"\u5fb3\u5cf6\u5e02","city_pref":71,"city_detail":"\u304b\u3061\u3069\u304d\u6a4b","zip_code":"7700939"},"124":{"city_order":1,"city_id":71001,"city_pref_name":"\u5fb3\u5cf6\u770c","city_name":"\u5fb3\u5cf6\u5e02","city_pref":71,"city_detail":"\u4e07\u4ee3\u753a","zip_code":"7700941"},"125":{"city_order":1,"city_id":71001,"city_pref_name":"\u5fb3\u5cf6\u770c","city_name":"\u5fb3\u5cf6\u5e02","city_pref":71,"city_detail":"\u662d\u548c\u753a","zip_code":"7700942"},"126":{"city_order":1,"city_id":71001,"city_pref_name":"\u5fb3\u5cf6\u770c","city_name":"\u5fb3\u5cf6\u5e02","city_pref":71,"city_detail":"\u4e2d\u662d\u548c\u753a","zip_code":"7700943"},"127":{"city_order":1,"city_id":71001,"city_pref_name":"\u5fb3\u5cf6\u770c","city_name":"\u5fb3\u5cf6\u5e02","city_pref":71,"city_detail":"\u5357\u662d\u548c\u753a","zip_code":"7700944"},"128":{"city_order":1,"city_id":71001,"city_pref_name":"\u5fb3\u5cf6\u770c","city_name":"\u5fb3\u5cf6\u5e02","city_pref":71,"city_detail":"\u6d25\u7530\u6d77\u5cb8\u753a","zip_code":"7708001"},"129":{"city_order":1,"city_id":71001,"city_pref_name":"\u5fb3\u5cf6\u770c","city_name":"\u5fb3\u5cf6\u5e02","city_pref":71,"city_detail":"\u6d25\u7530\u753a","zip_code":"7708002"},"130":{"city_order":1,"city_id":71001,"city_pref_name":"\u5fb3\u5cf6\u770c","city_name":"\u5fb3\u5cf6\u5e02","city_pref":71,"city_detail":"\u6d25\u7530\u672c\u753a","zip_code":"7708003"},"131":{"city_order":1,"city_id":71001,"city_pref_name":"\u5fb3\u5cf6\u770c","city_name":"\u5fb3\u5cf6\u5e02","city_pref":71,"city_detail":"\u6d25\u7530\u897f\u753a","zip_code":"7708004"},"132":{"city_order":1,"city_id":71001,"city_pref_name":"\u5fb3\u5cf6\u770c","city_name":"\u5fb3\u5cf6\u5e02","city_pref":71,"city_detail":"\u6d25\u7530\u6d5c\u4e4b\u753a","zip_code":"7708005"},"133":{"city_order":1,"city_id":71001,"city_pref_name":"\u5fb3\u5cf6\u770c","city_name":"\u5fb3\u5cf6\u5e02","city_pref":71,"city_detail":"\u65b0\u6d5c\u753a","zip_code":"7708006"},"134":{"city_order":1,"city_id":71001,"city_pref_name":"\u5fb3\u5cf6\u770c","city_name":"\u5fb3\u5cf6\u5e02","city_pref":71,"city_detail":"\u65b0\u6d5c\u672c\u753a","zip_code":"7708007"},"135":{"city_order":1,"city_id":71001,"city_pref_name":"\u5fb3\u5cf6\u770c","city_name":"\u5fb3\u5cf6\u5e02","city_pref":71,"city_detail":"\u897f\u65b0\u6d5c\u753a","zip_code":"7708008"},"136":{"city_order":1,"city_id":71001,"city_pref_name":"\u5fb3\u5cf6\u770c","city_name":"\u5fb3\u5cf6\u5e02","city_pref":71,"city_detail":"\u8ad6\u7530\u753a","zip_code":"7708011"},"137":{"city_order":1,"city_id":71001,"city_pref_name":"\u5fb3\u5cf6\u770c","city_name":"\u5fb3\u5cf6\u5e02","city_pref":71,"city_detail":"\u5927\u539f\u753a","zip_code":"7708012"},"138":{"city_order":1,"city_id":71001,"city_pref_name":"\u5fb3\u5cf6\u770c","city_name":"\u5fb3\u5cf6\u5e02","city_pref":71,"city_detail":"\u96d1\u8cc0\u753a","zip_code":"7708021"},"139":{"city_order":1,"city_id":71001,"city_pref_name":"\u5fb3\u5cf6\u770c","city_name":"\u5fb3\u5cf6\u5e02","city_pref":71,"city_detail":"\u5927\u677e\u753a","zip_code":"7708022"},"140":{"city_order":1,"city_id":71001,"city_pref_name":"\u5fb3\u5cf6\u770c","city_name":"\u5fb3\u5cf6\u5e02","city_pref":71,"city_detail":"\u52dd\u5360\u753a","zip_code":"7708023"},"141":{"city_order":1,"city_id":71001,"city_pref_name":"\u5fb3\u5cf6\u770c","city_name":"\u5fb3\u5cf6\u5e02","city_pref":71,"city_detail":"\u897f\u9808\u8cc0\u753a","zip_code":"7708024"},"142":{"city_order":1,"city_id":71001,"city_pref_name":"\u5fb3\u5cf6\u770c","city_name":"\u5fb3\u5cf6\u5e02","city_pref":71,"city_detail":"\u4e09\u8ed2\u5c4b\u753a","zip_code":"7708025"},"143":{"city_order":1,"city_id":71001,"city_pref_name":"\u5fb3\u5cf6\u770c","city_name":"\u5fb3\u5cf6\u5e02","city_pref":71,"city_detail":"\u5927\u8c37\u753a","zip_code":"7708031"},"144":{"city_order":1,"city_id":71001,"city_pref_name":"\u5fb3\u5cf6\u770c","city_name":"\u5fb3\u5cf6\u5e02","city_pref":71,"city_detail":"\u5317\u5c71\u753a","zip_code":"7708032"},"145":{"city_order":1,"city_id":71001,"city_pref_name":"\u5fb3\u5cf6\u770c","city_name":"\u5fb3\u5cf6\u5e02","city_pref":71,"city_detail":"\u65b9\u4e0a\u753a","zip_code":"7708033"},"146":{"city_order":1,"city_id":71001,"city_pref_name":"\u5fb3\u5cf6\u770c","city_name":"\u5fb3\u5cf6\u5e02","city_pref":71,"city_detail":"\u4e0a\u516b\u4e07\u753a","zip_code":"7708040"},"147":{"city_order":1,"city_id":71001,"city_pref_name":"\u5fb3\u5cf6\u770c","city_name":"\u5fb3\u5cf6\u5e02","city_pref":71,"city_detail":"\u4e0a\u516b\u4e07\u753a\u897f\u5c71","zip_code":"7708041"},"148":{"city_order":1,"city_id":71001,"city_pref_name":"\u5fb3\u5cf6\u770c","city_name":"\u5fb3\u5cf6\u5e02","city_pref":71,"city_detail":"\u6c96\u6d5c\u753a","zip_code":"7708051"},"149":{"city_order":1,"city_id":71001,"city_pref_name":"\u5fb3\u5cf6\u770c","city_name":"\u5fb3\u5cf6\u5e02","city_pref":71,"city_detail":"\u6c96\u6d5c","zip_code":"7708052"},"150":{"city_order":1,"city_id":71001,"city_pref_name":"\u5fb3\u5cf6\u770c","city_name":"\u5fb3\u5cf6\u5e02","city_pref":71,"city_detail":"\u6c96\u6d5c\u6771","zip_code":"7708053"},"151":{"city_order":1,"city_id":71001,"city_pref_name":"\u5fb3\u5cf6\u770c","city_name":"\u5fb3\u5cf6\u5e02","city_pref":71,"city_detail":"\u5c71\u57ce\u897f","zip_code":"7708054"},"152":{"city_order":1,"city_id":71001,"city_pref_name":"\u5fb3\u5cf6\u770c","city_name":"\u5fb3\u5cf6\u5e02","city_pref":71,"city_detail":"\u5c71\u57ce\u753a","zip_code":"7708055"},"153":{"city_order":1,"city_id":71001,"city_pref_name":"\u5fb3\u5cf6\u770c","city_name":"\u5fb3\u5cf6\u5e02","city_pref":71,"city_detail":"\u554f\u5c4b\u753a","zip_code":"7708056"},"154":{"city_order":1,"city_id":71001,"city_pref_name":"\u5fb3\u5cf6\u770c","city_name":"\u5fb3\u5cf6\u5e02","city_pref":71,"city_detail":"\u897f\u4e8c\u8ed2\u5c4b\u753a","zip_code":"7708061"},"155":{"city_order":1,"city_id":71001,"city_pref_name":"\u5fb3\u5cf6\u770c","city_name":"\u5fb3\u5cf6\u5e02","city_pref":71,"city_detail":"\u5357\u4e8c\u8ed2\u5c4b\u753a","zip_code":"7708063"},"156":{"city_order":1,"city_id":71001,"city_pref_name":"\u5fb3\u5cf6\u770c","city_name":"\u5fb3\u5cf6\u5e02","city_pref":71,"city_detail":"\u57ce\u5357\u753a","zip_code":"7708064"},"157":{"city_order":1,"city_id":71001,"city_pref_name":"\u5fb3\u5cf6\u770c","city_name":"\u5fb3\u5cf6\u5e02","city_pref":71,"city_detail":"\u516b\u4e07\u753a","zip_code":"7708070"},"158":{"city_order":1,"city_id":71001,"city_pref_name":"\u5fb3\u5cf6\u770c","city_name":"\u5fb3\u5cf6\u5e02","city_pref":71,"city_detail":"\u516b\u4e07\u753a","zip_code":"7708071"},"159":{"city_order":1,"city_id":71001,"city_pref_name":"\u5fb3\u5cf6\u770c","city_name":"\u5fb3\u5cf6\u5e02","city_pref":71,"city_detail":"\u516b\u4e07\u753a","zip_code":"7708072"},"160":{"city_order":1,"city_id":71001,"city_pref_name":"\u5fb3\u5cf6\u770c","city_name":"\u5fb3\u5cf6\u5e02","city_pref":71,"city_detail":"\u516b\u4e07\u753a","zip_code":"7708073"},"161":{"city_order":1,"city_id":71001,"city_pref_name":"\u5fb3\u5cf6\u770c","city_name":"\u5fb3\u5cf6\u5e02","city_pref":71,"city_detail":"\u516b\u4e07\u753a","zip_code":"7708074"},"162":{"city_order":1,"city_id":71001,"city_pref_name":"\u5fb3\u5cf6\u770c","city_name":"\u5fb3\u5cf6\u5e02","city_pref":71,"city_detail":"\u516b\u4e07\u753a","zip_code":"7708075"},"163":{"city_order":1,"city_id":71001,"city_pref_name":"\u5fb3\u5cf6\u770c","city_name":"\u5fb3\u5cf6\u5e02","city_pref":71,"city_detail":"\u516b\u4e07\u753a","zip_code":"7708076"},"164":{"city_order":1,"city_id":71001,"city_pref_name":"\u5fb3\u5cf6\u770c","city_name":"\u5fb3\u5cf6\u5e02","city_pref":71,"city_detail":"\u516b\u4e07\u753a","zip_code":"7708077"},"165":{"city_order":1,"city_id":71001,"city_pref_name":"\u5fb3\u5cf6\u770c","city_name":"\u5fb3\u5cf6\u5e02","city_pref":71,"city_detail":"\u516b\u4e07\u753a","zip_code":"7708078"},"166":{"city_order":1,"city_id":71001,"city_pref_name":"\u5fb3\u5cf6\u770c","city_name":"\u5fb3\u5cf6\u5e02","city_pref":71,"city_detail":"\u516b\u4e07\u753a","zip_code":"7708079"},"167":{"city_order":1,"city_id":71001,"city_pref_name":"\u5fb3\u5cf6\u770c","city_name":"\u5fb3\u5cf6\u5e02","city_pref":71,"city_detail":"\u516b\u4e07\u753a","zip_code":"7708081"},"168":{"city_order":1,"city_id":71001,"city_pref_name":"\u5fb3\u5cf6\u770c","city_name":"\u5fb3\u5cf6\u5e02","city_pref":71,"city_detail":"\u516b\u4e07\u753a","zip_code":"7708082"},"169":{"city_order":1,"city_id":71001,"city_pref_name":"\u5fb3\u5cf6\u770c","city_name":"\u5fb3\u5cf6\u5e02","city_pref":71,"city_detail":"\u516b\u4e07\u753a","zip_code":"7708083"},"170":{"city_order":1,"city_id":71001,"city_pref_name":"\u5fb3\u5cf6\u770c","city_name":"\u5fb3\u5cf6\u5e02","city_pref":71,"city_detail":"\u516b\u4e07\u753a","zip_code":"7708084"},"city_list":{"71001":"\u5fb3\u5cf6\u5e02","71002":"\u9cf4\u9580\u5e02","71003":"\u5c0f\u677e\u5cf6\u5e02","71004":"\u963f\u5357\u5e02","71005":"\u5409\u91ce\u5ddd\u5e02","71006":"\u963f\u6ce2\u5e02","71007":"\u7f8e\u99ac\u5e02","71008":"\u4e09\u597d\u5e02","71009":"\u52dd\u6d66\u90e1\u52dd\u6d66\u753a","71010":"\u52dd\u6d66\u90e1\u4e0a\u52dd\u753a","71011":"\u540d\u6771\u90e1\u4f50\u90a3\u6cb3\u5185\u6751","71012":"\u540d\u897f\u90e1\u77f3\u4e95\u753a","71013":"\u540d\u897f\u90e1\u795e\u5c71\u753a","71014":"\u90a3\u8cc0\u90e1\u90a3\u8cc0\u753a","71015":"\u6d77\u90e8\u90e1\u725f\u5c90\u753a","71016":"\u6d77\u90e8\u90e1\u7f8e\u6ce2\u753a","71017":"\u6d77\u90e8\u90e1\u6d77\u967d\u753a","71018":"\u677f\u91ce\u90e1\u677e\u8302\u753a","71019":"\u677f\u91ce\u90e1\u5317\u5cf6\u753a","71020":"\u677f\u91ce\u90e1\u85cd\u4f4f\u753a","71021":"\u677f\u91ce\u90e1\u677f\u91ce\u753a","71022":"\u677f\u91ce\u90e1\u4e0a\u677f\u753a","71023":"\u7f8e\u99ac\u90e1\u3064\u308b\u304e\u753a","71024":"\u4e09\u597d\u90e1\u6771\u307f\u3088\u3057\u753a","71999":"\uff08\u65e7\u4f4f\u6240\uff09"}}