{"0":{"city_order":5,"city_id":83005,"city_pref_name":"\u9577\u5d0e\u770c","city_name":"\u5927\u6751\u5e02","city_pref":83,"city_detail":"","zip_code":"8560000"},"1":{"city_order":5,"city_id":83005,"city_pref_name":"\u9577\u5d0e\u770c","city_name":"\u5927\u6751\u5e02","city_pref":83,"city_detail":"\u6b66\u7559\u8def\u753a","zip_code":"8560001"},"2":{"city_order":5,"city_id":83005,"city_pref_name":"\u9577\u5d0e\u770c","city_name":"\u5927\u6751\u5e02","city_pref":83,"city_detail":"\u6771\u91ce\u5cb3\u753a","zip_code":"8560002"},"3":{"city_order":5,"city_id":83005,"city_pref_name":"\u9577\u5d0e\u770c","city_name":"\u5927\u6751\u5e02","city_pref":83,"city_detail":"\u91ce\u5cb3\u753a","zip_code":"8560003"},"4":{"city_order":5,"city_id":83005,"city_pref_name":"\u9577\u5d0e\u770c","city_name":"\u5927\u6751\u5e02","city_pref":83,"city_detail":"\u7acb\u798f\u5bfa\u753a","zip_code":"8560004"},"5":{"city_order":5,"city_id":83005,"city_pref_name":"\u9577\u5d0e\u770c","city_name":"\u5927\u6751\u5e02","city_pref":83,"city_detail":"\u5f25\u52d2\u5bfa\u753a","zip_code":"8560005"},"6":{"city_order":5,"city_id":83005,"city_pref_name":"\u9577\u5d0e\u770c","city_name":"\u5927\u6751\u5e02","city_pref":83,"city_detail":"\u798f\u91cd\u753a","zip_code":"8560006"},"7":{"city_order":5,"city_id":83005,"city_pref_name":"\u9577\u5d0e\u770c","city_name":"\u5927\u6751\u5e02","city_pref":83,"city_detail":"\u8349\u5834\u753a","zip_code":"8560007"},"8":{"city_order":5,"city_id":83005,"city_pref_name":"\u9577\u5d0e\u770c","city_name":"\u5927\u6751\u5e02","city_pref":83,"city_detail":"\u677e\u539f","zip_code":"8560008"},"9":{"city_order":5,"city_id":83005,"city_pref_name":"\u9577\u5d0e\u770c","city_name":"\u5927\u6751\u5e02","city_pref":83,"city_detail":"\u677e\u539f\u672c\u753a","zip_code":"8560009"},"10":{"city_order":5,"city_id":83005,"city_pref_name":"\u9577\u5d0e\u770c","city_name":"\u5927\u6751\u5e02","city_pref":83,"city_detail":"\u91cd\u4e95\u7530\u753a","zip_code":"8560011"},"11":{"city_order":5,"city_id":83005,"city_pref_name":"\u9577\u5d0e\u770c","city_name":"\u5927\u6751\u5e02","city_pref":83,"city_detail":"\u9ed2\u6728\u753a","zip_code":"8560012"},"12":{"city_order":5,"city_id":83005,"city_pref_name":"\u9577\u5d0e\u770c","city_name":"\u5927\u6751\u5e02","city_pref":83,"city_detail":"\u4e2d\u5cb3\u753a","zip_code":"8560013"},"13":{"city_order":5,"city_id":83005,"city_pref_name":"\u9577\u5d0e\u770c","city_name":"\u5927\u6751\u5e02","city_pref":83,"city_detail":"\u7530\u4e0b\u753a","zip_code":"8560014"},"14":{"city_order":5,"city_id":83005,"city_pref_name":"\u9577\u5d0e\u770c","city_name":"\u5927\u6751\u5e02","city_pref":83,"city_detail":"\u5bae\u4ee3\u753a","zip_code":"8560015"},"15":{"city_order":5,"city_id":83005,"city_pref_name":"\u9577\u5d0e\u770c","city_name":"\u5927\u6751\u5e02","city_pref":83,"city_detail":"\u539f\u753a","zip_code":"8560016"},"16":{"city_order":5,"city_id":83005,"city_pref_name":"\u9577\u5d0e\u770c","city_name":"\u5927\u6751\u5e02","city_pref":83,"city_detail":"\u8352\u702c\u753a","zip_code":"8560017"},"17":{"city_order":5,"city_id":83005,"city_pref_name":"\u9577\u5d0e\u770c","city_name":"\u5927\u6751\u5e02","city_pref":83,"city_detail":"\u4eca\u5bcc\u753a","zip_code":"8560018"},"18":{"city_order":5,"city_id":83005,"city_pref_name":"\u9577\u5d0e\u770c","city_name":"\u5927\u6751\u5e02","city_pref":83,"city_detail":"\u91ce\u7530\u753a","zip_code":"8560019"},"19":{"city_order":5,"city_id":83005,"city_pref_name":"\u9577\u5d0e\u770c","city_name":"\u5927\u6751\u5e02","city_pref":83,"city_detail":"\u5c0f\u8def\u53e3\u672c\u753a","zip_code":"8560020"},"20":{"city_order":5,"city_id":83005,"city_pref_name":"\u9577\u5d0e\u770c","city_name":"\u5927\u6751\u5e02","city_pref":83,"city_detail":"\u9b3c\u6a4b\u753a","zip_code":"8560021"},"21":{"city_order":5,"city_id":83005,"city_pref_name":"\u9577\u5d0e\u770c","city_name":"\u5927\u6751\u5e02","city_pref":83,"city_detail":"\u96c4\u30b1\u539f\u753a","zip_code":"8560022"},"22":{"city_order":5,"city_id":83005,"city_pref_name":"\u9577\u5d0e\u770c","city_name":"\u5927\u6751\u5e02","city_pref":83,"city_detail":"\u4e0a\u8acf\u8a2a\u753a","zip_code":"8560023"},"23":{"city_order":5,"city_id":83005,"city_pref_name":"\u9577\u5d0e\u770c","city_name":"\u5927\u6751\u5e02","city_pref":83,"city_detail":"\u8acf\u8a2a","zip_code":"8560024"},"24":{"city_order":5,"city_id":83005,"city_pref_name":"\u9577\u5d0e\u770c","city_name":"\u5927\u6751\u5e02","city_pref":83,"city_detail":"\u5c0f\u8def\u53e3\u753a","zip_code":"8560025"},"25":{"city_order":5,"city_id":83005,"city_pref_name":"\u9577\u5d0e\u770c","city_name":"\u5927\u6751\u5e02","city_pref":83,"city_detail":"\u6c60\u7530","zip_code":"8560026"},"26":{"city_order":5,"city_id":83005,"city_pref_name":"\u9577\u5d0e\u770c","city_name":"\u5927\u6751\u5e02","city_pref":83,"city_detail":"\u690d\u677e","zip_code":"8560027"},"27":{"city_order":5,"city_id":83005,"city_pref_name":"\u9577\u5d0e\u770c","city_name":"\u5927\u6751\u5e02","city_pref":83,"city_detail":"\u5742\u53e3\u753a","zip_code":"8560028"},"28":{"city_order":5,"city_id":83005,"city_pref_name":"\u9577\u5d0e\u770c","city_name":"\u5927\u6751\u5e02","city_pref":83,"city_detail":"\u6c60\u7530\u65b0\u753a","zip_code":"8560029"},"29":{"city_order":5,"city_id":83005,"city_pref_name":"\u9577\u5d0e\u770c","city_name":"\u5927\u6751\u5e02","city_pref":83,"city_detail":"\u4e09\u57ce\u753a","zip_code":"8560031"},"30":{"city_order":5,"city_id":83005,"city_pref_name":"\u9577\u5d0e\u770c","city_name":"\u5927\u6751\u5e02","city_pref":83,"city_detail":"\u6771\u5927\u6751","zip_code":"8560032"},"31":{"city_order":5,"city_id":83005,"city_pref_name":"\u9577\u5d0e\u770c","city_name":"\u5927\u6751\u5e02","city_pref":83,"city_detail":"\u8352\u5e73\u753a","zip_code":"8560033"},"32":{"city_order":5,"city_id":83005,"city_pref_name":"\u9577\u5d0e\u770c","city_name":"\u5927\u6751\u5e02","city_pref":83,"city_detail":"\u6c34\u8a08\u753a","zip_code":"8560034"},"33":{"city_order":5,"city_id":83005,"city_pref_name":"\u9577\u5d0e\u770c","city_name":"\u5927\u6751\u5e02","city_pref":83,"city_detail":"\u6b66\u90e8\u753a","zip_code":"8560035"},"34":{"city_order":5,"city_id":83005,"city_pref_name":"\u9577\u5d0e\u770c","city_name":"\u5927\u6751\u5e02","city_pref":83,"city_detail":"\u5fb3\u6cc9\u5ddd\u5185\u753a","zip_code":"8560041"},"35":{"city_order":5,"city_id":83005,"city_pref_name":"\u9577\u5d0e\u770c","city_name":"\u5927\u6751\u5e02","city_pref":83,"city_detail":"\u5e73\u753a","zip_code":"8560042"},"36":{"city_order":5,"city_id":83005,"city_pref_name":"\u9577\u5d0e\u770c","city_name":"\u5927\u6751\u5e02","city_pref":83,"city_detail":"\u5c0f\u5ddd\u5185\u753a","zip_code":"8560043"},"37":{"city_order":5,"city_id":83005,"city_pref_name":"\u9577\u5d0e\u770c","city_name":"\u5927\u6751\u5e02","city_pref":83,"city_detail":"\u5ca9\u677e\u753a","zip_code":"8560044"},"38":{"city_order":5,"city_id":83005,"city_pref_name":"\u9577\u5d0e\u770c","city_name":"\u5927\u6751\u5e02","city_pref":83,"city_detail":"\u5411\u6728\u5834\u753a","zip_code":"8560045"},"39":{"city_order":5,"city_id":83005,"city_pref_name":"\u9577\u5d0e\u770c","city_name":"\u5927\u6751\u5e02","city_pref":83,"city_detail":"\u6728\u5834","zip_code":"8560046"},"40":{"city_order":5,"city_id":83005,"city_pref_name":"\u9577\u5d0e\u770c","city_name":"\u5927\u6751\u5e02","city_pref":83,"city_detail":"\u9808\u7530\u30ce\u6728\u753a","zip_code":"8560047"},"41":{"city_order":5,"city_id":83005,"city_pref_name":"\u9577\u5d0e\u770c","city_name":"\u5927\u6751\u5e02","city_pref":83,"city_detail":"\u8d64\u4f50\u53e4\u753a","zip_code":"8560048"},"42":{"city_order":5,"city_id":83005,"city_pref_name":"\u9577\u5d0e\u770c","city_name":"\u5927\u6751\u5e02","city_pref":83,"city_detail":"\u5bff\u53e4\u753a","zip_code":"8560801"},"43":{"city_order":5,"city_id":83005,"city_pref_name":"\u9577\u5d0e\u770c","city_name":"\u5927\u6751\u5e02","city_pref":83,"city_detail":"\u7686\u540c\u753a","zip_code":"8560802"},"44":{"city_order":5,"city_id":83005,"city_pref_name":"\u9577\u5d0e\u770c","city_name":"\u5927\u6751\u5e02","city_pref":83,"city_detail":"\u7af9\u677e\u753a","zip_code":"8560803"},"45":{"city_order":5,"city_id":83005,"city_pref_name":"\u9577\u5d0e\u770c","city_name":"\u5927\u6751\u5e02","city_pref":83,"city_detail":"\u5927\u5ddd\u7530\u753a","zip_code":"8560804"},"46":{"city_order":5,"city_id":83005,"city_pref_name":"\u9577\u5d0e\u770c","city_name":"\u5927\u6751\u5e02","city_pref":83,"city_detail":"\u7af9\u677e\u672c\u753a","zip_code":"8560805"},"47":{"city_order":5,"city_id":83005,"city_pref_name":"\u9577\u5d0e\u770c","city_name":"\u5927\u6751\u5e02","city_pref":83,"city_detail":"\u5bcc\u306e\u539f","zip_code":"8560806"},"48":{"city_order":5,"city_id":83005,"city_pref_name":"\u9577\u5d0e\u770c","city_name":"\u5927\u6751\u5e02","city_pref":83,"city_detail":"\u5bae\u5c0f\u8def","zip_code":"8560807"},"49":{"city_order":5,"city_id":83005,"city_pref_name":"\u9577\u5d0e\u770c","city_name":"\u5927\u6751\u5e02","city_pref":83,"city_detail":"\u9ed2\u4e38\u753a","zip_code":"8560808"},"50":{"city_order":5,"city_id":83005,"city_pref_name":"\u9577\u5d0e\u770c","city_name":"\u5927\u6751\u5e02","city_pref":83,"city_detail":"\u6c96\u7530\u753a","zip_code":"8560809"},"51":{"city_order":5,"city_id":83005,"city_pref_name":"\u9577\u5d0e\u770c","city_name":"\u5927\u6751\u5e02","city_pref":83,"city_detail":"\u539f\u53e3\u753a","zip_code":"8560811"},"52":{"city_order":5,"city_id":83005,"city_pref_name":"\u9577\u5d0e\u770c","city_name":"\u5927\u6751\u5e02","city_pref":83,"city_detail":"\u685c\u99ac\u5834","zip_code":"8560812"},"53":{"city_order":5,"city_id":83005,"city_pref_name":"\u9577\u5d0e\u770c","city_name":"\u5927\u6751\u5e02","city_pref":83,"city_detail":"\u897f\u5927\u6751\u672c\u753a","zip_code":"8560813"},"54":{"city_order":5,"city_id":83005,"city_pref_name":"\u9577\u5d0e\u770c","city_name":"\u5927\u6751\u5e02","city_pref":83,"city_detail":"\u677e\u4e26","zip_code":"8560814"},"55":{"city_order":5,"city_id":83005,"city_pref_name":"\u9577\u5d0e\u770c","city_name":"\u5927\u6751\u5e02","city_pref":83,"city_detail":"\u68ee\u5712\u753a","zip_code":"8560815"},"56":{"city_order":5,"city_id":83005,"city_pref_name":"\u9577\u5d0e\u770c","city_name":"\u5927\u6751\u5e02","city_pref":83,"city_detail":"\u7b95\u5cf6\u753a","zip_code":"8560816"},"57":{"city_order":5,"city_id":83005,"city_pref_name":"\u9577\u5d0e\u770c","city_name":"\u5927\u6751\u5e02","city_pref":83,"city_detail":"\u53e4\u8cc0\u5cf6\u753a","zip_code":"8560817"},"58":{"city_order":5,"city_id":83005,"city_pref_name":"\u9577\u5d0e\u770c","city_name":"\u5927\u6751\u5e02","city_pref":83,"city_detail":"\u4eca\u6d25\u753a","zip_code":"8560818"},"59":{"city_order":5,"city_id":83005,"city_pref_name":"\u9577\u5d0e\u770c","city_name":"\u5927\u6751\u5e02","city_pref":83,"city_detail":"\u5354\u548c\u753a","zip_code":"8560820"},"60":{"city_order":5,"city_id":83005,"city_pref_name":"\u9577\u5d0e\u770c","city_name":"\u5927\u6751\u5e02","city_pref":83,"city_detail":"\u897f\u4e7e\u99ac\u5834\u753a","zip_code":"8560821"},"61":{"city_order":5,"city_id":83005,"city_pref_name":"\u9577\u5d0e\u770c","city_name":"\u5927\u6751\u5e02","city_pref":83,"city_detail":"\u53e4\u753a","zip_code":"8560822"},"62":{"city_order":5,"city_id":83005,"city_pref_name":"\u9577\u5d0e\u770c","city_name":"\u5927\u6751\u5e02","city_pref":83,"city_detail":"\u4e7e\u99ac\u5834\u753a","zip_code":"8560823"},"63":{"city_order":5,"city_id":83005,"city_pref_name":"\u9577\u5d0e\u770c","city_name":"\u5927\u6751\u5e02","city_pref":83,"city_detail":"\u6c34\u7530\u753a","zip_code":"8560824"},"64":{"city_order":5,"city_id":83005,"city_pref_name":"\u9577\u5d0e\u770c","city_name":"\u5927\u6751\u5e02","city_pref":83,"city_detail":"\u897f\u4e09\u57ce\u753a","zip_code":"8560825"},"65":{"city_order":5,"city_id":83005,"city_pref_name":"\u9577\u5d0e\u770c","city_name":"\u5927\u6751\u5e02","city_pref":83,"city_detail":"\u6771\u4e09\u57ce\u753a","zip_code":"8560826"},"66":{"city_order":5,"city_id":83005,"city_pref_name":"\u9577\u5d0e\u770c","city_name":"\u5927\u6751\u5e02","city_pref":83,"city_detail":"\u6c34\u4e3b\u753a","zip_code":"8560827"},"67":{"city_order":5,"city_id":83005,"city_pref_name":"\u9577\u5d0e\u770c","city_name":"\u5927\u6751\u5e02","city_pref":83,"city_detail":"\u676d\u51fa\u6d25","zip_code":"8560828"},"68":{"city_order":5,"city_id":83005,"city_pref_name":"\u9577\u5d0e\u770c","city_name":"\u5927\u6751\u5e02","city_pref":83,"city_detail":"\u677e\u5c71\u753a","zip_code":"8560829"},"69":{"city_order":5,"city_id":83005,"city_pref_name":"\u9577\u5d0e\u770c","city_name":"\u5927\u6751\u5e02","city_pref":83,"city_detail":"\u6771\u672c\u753a","zip_code":"8560831"},"70":{"city_order":5,"city_id":83005,"city_pref_name":"\u9577\u5d0e\u770c","city_name":"\u5927\u6751\u5e02","city_pref":83,"city_detail":"\u672c\u753a","zip_code":"8560832"},"71":{"city_order":5,"city_id":83005,"city_pref_name":"\u9577\u5d0e\u770c","city_name":"\u5927\u6751\u5e02","city_pref":83,"city_detail":"\u7247\u753a","zip_code":"8560833"},"72":{"city_order":5,"city_id":83005,"city_pref_name":"\u9577\u5d0e\u770c","city_name":"\u5927\u6751\u5e02","city_pref":83,"city_detail":"\u7396\u5cf6","zip_code":"8560834"},"73":{"city_order":5,"city_id":83005,"city_pref_name":"\u9577\u5d0e\u770c","city_name":"\u5927\u6751\u5e02","city_pref":83,"city_detail":"\u4e45\u539f","zip_code":"8560835"},"74":{"city_order":5,"city_id":83005,"city_pref_name":"\u9577\u5d0e\u770c","city_name":"\u5927\u6751\u5e02","city_pref":83,"city_detail":"\u5e78\u753a","zip_code":"8560836"},"75":{"city_order":5,"city_id":83005,"city_pref_name":"\u9577\u5d0e\u770c","city_name":"\u5927\u6751\u5e02","city_pref":83,"city_detail":"\u897f\u672c\u753a","zip_code":"8560837"},"76":{"city_order":5,"city_id":83005,"city_pref_name":"\u9577\u5d0e\u770c","city_name":"\u5927\u6751\u5e02","city_pref":83,"city_detail":"\u9670\u5e73\u753a","zip_code":"8560841"},"77":{"city_order":5,"city_id":83005,"city_pref_name":"\u9577\u5d0e\u770c","city_name":"\u5927\u6751\u5e02","city_pref":83,"city_detail":"\u4e2d\u91cc\u753a","zip_code":"8560842"},"78":{"city_order":5,"city_id":83005,"city_pref_name":"\u9577\u5d0e\u770c","city_name":"\u5927\u6751\u5e02","city_pref":83,"city_detail":"\u4eca\u6751\u753a","zip_code":"8560843"},"79":{"city_order":5,"city_id":83005,"city_pref_name":"\u9577\u5d0e\u770c","city_name":"\u5927\u6751\u5e02","city_pref":83,"city_detail":"\u6e9d\u9678\u753a","zip_code":"8560844"},"80":{"city_order":5,"city_id":83005,"city_pref_name":"\u9577\u5d0e\u770c","city_name":"\u5927\u6751\u5e02","city_pref":83,"city_detail":"\u5927\u91cc\u753a","zip_code":"8560845"},"81":{"city_order":5,"city_id":83005,"city_pref_name":"\u9577\u5d0e\u770c","city_name":"\u5927\u6751\u5e02","city_pref":83,"city_detail":"\u65e5\u6cca\u753a","zip_code":"8560846"},"82":{"city_order":5,"city_id":83005,"city_pref_name":"\u9577\u5d0e\u770c","city_name":"\u5927\u6751\u5e02","city_pref":83,"city_detail":"\u897f\u90e8\u753a","zip_code":"8560847"},"city_list":{"83001":"\u9577\u5d0e\u5e02","83002":"\u4f50\u4e16\u4fdd\u5e02","83003":"\u5cf6\u539f\u5e02","83004":"\u8aeb\u65e9\u5e02","83005":"\u5927\u6751\u5e02","83006":"\u5e73\u6238\u5e02","83007":"\u677e\u6d66\u5e02","83008":"\u5bfe\u99ac\u5e02","83009":"\u58f1\u5c90\u5e02","83010":"\u4e94\u5cf6\u5e02","83011":"\u897f\u6d77\u5e02","83012":"\u96f2\u4ed9\u5e02","83013":"\u5357\u5cf6\u539f\u5e02","83014":"\u897f\u5f7c\u6775\u90e1\u9577\u4e0e\u753a","83015":"\u897f\u5f7c\u6775\u90e1\u6642\u6d25\u753a","83016":"\u6771\u5f7c\u6775\u90e1\u6771\u5f7c\u6775\u753a","83017":"\u6771\u5f7c\u6775\u90e1\u5ddd\u68da\u753a","83018":"\u6771\u5f7c\u6775\u90e1\u6ce2\u4f50\u898b\u753a","83019":"\u5317\u677e\u6d66\u90e1\u5c0f\u5024\u8cc0\u753a","83020":"\u5317\u677e\u6d66\u90e1\u4f50\u3005\u753a","83021":"\u5357\u677e\u6d66\u90e1\u65b0\u4e0a\u4e94\u5cf6\u753a","83999":"\uff08\u65e7\u4f4f\u6240\uff09"}}