{"0":{"city_order":4,"city_id":14004,"city_pref_name":"\u5bae\u57ce\u770c","city_name":"\u4ed9\u53f0\u5e02\u592a\u767d\u533a","city_pref":14,"city_detail":"","zip_code":"9820000"},"1":{"city_order":4,"city_id":14004,"city_pref_name":"\u5bae\u57ce\u770c","city_name":"\u4ed9\u53f0\u5e02\u592a\u767d\u533a","city_pref":14,"city_detail":"\u516b\u672c\u677e","zip_code":"9820001"},"2":{"city_order":4,"city_id":14004,"city_pref_name":"\u5bae\u57ce\u770c","city_name":"\u4ed9\u53f0\u5e02\u592a\u767d\u533a","city_pref":14,"city_detail":"\u98ef\u7530","zip_code":"9820002"},"3":{"city_order":4,"city_id":14004,"city_pref_name":"\u5bae\u57ce\u770c","city_name":"\u4ed9\u53f0\u5e02\u592a\u767d\u533a","city_pref":14,"city_detail":"\u90e1\u5c71","zip_code":"9820003"},"4":{"city_order":4,"city_id":14004,"city_pref_name":"\u5bae\u57ce\u770c","city_name":"\u4ed9\u53f0\u5e02\u592a\u767d\u533a","city_pref":14,"city_detail":"\u6771\u5927\u91ce\u7530","zip_code":"9820004"},"5":{"city_order":4,"city_id":14004,"city_pref_name":"\u5bae\u57ce\u770c","city_name":"\u4ed9\u53f0\u5e02\u592a\u767d\u533a","city_pref":14,"city_detail":"\u8acf\u8a2a\u753a","zip_code":"9820005"},"6":{"city_order":4,"city_id":14004,"city_pref_name":"\u5bae\u57ce\u770c","city_name":"\u4ed9\u53f0\u5e02\u592a\u767d\u533a","city_pref":14,"city_detail":"\u6771\u90e1\u5c71","zip_code":"9820006"},"7":{"city_order":4,"city_id":14004,"city_pref_name":"\u5bae\u57ce\u770c","city_name":"\u4ed9\u53f0\u5e02\u592a\u767d\u533a","city_pref":14,"city_detail":"\u3042\u3059\u3068\u9577\u753a","zip_code":"9820007"},"8":{"city_order":4,"city_id":14004,"city_pref_name":"\u5bae\u57ce\u770c","city_name":"\u4ed9\u53f0\u5e02\u592a\u767d\u533a","city_pref":14,"city_detail":"\u9577\u753a","zip_code":"9820011"},"9":{"city_order":4,"city_id":14004,"city_pref_name":"\u5bae\u57ce\u770c","city_name":"\u4ed9\u53f0\u5e02\u592a\u767d\u533a","city_pref":14,"city_detail":"\u9577\u753a\u5357","zip_code":"9820012"},"10":{"city_order":4,"city_id":14004,"city_pref_name":"\u5bae\u57ce\u770c","city_name":"\u4ed9\u53f0\u5e02\u592a\u767d\u533a","city_pref":14,"city_detail":"\u592a\u5b50\u5802","zip_code":"9820013"},"11":{"city_order":4,"city_id":14004,"city_pref_name":"\u5bae\u57ce\u770c","city_name":"\u4ed9\u53f0\u5e02\u592a\u767d\u533a","city_pref":14,"city_detail":"\u5927\u91ce\u7530","zip_code":"9820014"},"12":{"city_order":4,"city_id":14004,"city_pref_name":"\u5bae\u57ce\u770c","city_name":"\u4ed9\u53f0\u5e02\u592a\u767d\u533a","city_pref":14,"city_detail":"\u5357\u5927\u91ce\u7530","zip_code":"9820015"},"13":{"city_order":4,"city_id":14004,"city_pref_name":"\u5bae\u57ce\u770c","city_name":"\u4ed9\u53f0\u5e02\u592a\u767d\u533a","city_pref":14,"city_detail":"\u7dd1\u30b1\u4e18","zip_code":"9820021"},"14":{"city_order":4,"city_id":14004,"city_pref_name":"\u5bae\u57ce\u770c","city_name":"\u4ed9\u53f0\u5e02\u592a\u767d\u533a","city_pref":14,"city_detail":"\u9e7f\u91ce\u672c\u753a","zip_code":"9820022"},"15":{"city_order":4,"city_id":14004,"city_pref_name":"\u5bae\u57ce\u770c","city_name":"\u4ed9\u53f0\u5e02\u592a\u767d\u533a","city_pref":14,"city_detail":"\u9e7f\u91ce","zip_code":"9820023"},"16":{"city_order":4,"city_id":14004,"city_pref_name":"\u5bae\u57ce\u770c","city_name":"\u4ed9\u53f0\u5e02\u592a\u767d\u533a","city_pref":14,"city_detail":"\u7802\u62bc\u5357\u753a","zip_code":"9820024"},"17":{"city_order":4,"city_id":14004,"city_pref_name":"\u5bae\u57ce\u770c","city_name":"\u4ed9\u53f0\u5e02\u592a\u767d\u533a","city_pref":14,"city_detail":"\u7802\u62bc\u753a","zip_code":"9820025"},"18":{"city_order":4,"city_id":14004,"city_pref_name":"\u5bae\u57ce\u770c","city_name":"\u4ed9\u53f0\u5e02\u592a\u767d\u533a","city_pref":14,"city_detail":"\u571f\u624b\u5185","zip_code":"9820026"},"19":{"city_order":4,"city_id":14004,"city_pref_name":"\u5bae\u57ce\u770c","city_name":"\u4ed9\u53f0\u5e02\u592a\u767d\u533a","city_pref":14,"city_detail":"\u5927\u5852\u753a","zip_code":"9820027"},"20":{"city_order":4,"city_id":14004,"city_pref_name":"\u5bae\u57ce\u770c","city_name":"\u4ed9\u53f0\u5e02\u592a\u767d\u533a","city_pref":14,"city_detail":"\u6cc9\u5d0e","zip_code":"9820031"},"21":{"city_order":4,"city_id":14004,"city_pref_name":"\u5bae\u57ce\u770c","city_name":"\u4ed9\u53f0\u5e02\u592a\u767d\u533a","city_pref":14,"city_detail":"\u5bcc\u6ca2","zip_code":"9820032"},"22":{"city_order":4,"city_id":14004,"city_pref_name":"\u5bae\u57ce\u770c","city_name":"\u4ed9\u53f0\u5e02\u592a\u767d\u533a","city_pref":14,"city_detail":"\u5bcc\u7530","zip_code":"9820033"},"23":{"city_order":4,"city_id":14004,"city_pref_name":"\u5bae\u57ce\u770c","city_name":"\u4ed9\u53f0\u5e02\u592a\u767d\u533a","city_pref":14,"city_detail":"\u897f\u591a\u8cc0","zip_code":"9820034"},"24":{"city_order":4,"city_id":14004,"city_pref_name":"\u5bae\u57ce\u770c","city_name":"\u4ed9\u53f0\u5e02\u592a\u767d\u533a","city_pref":14,"city_detail":"\u5927\u8c37\u5730","zip_code":"9820035"},"25":{"city_order":4,"city_id":14004,"city_pref_name":"\u5bae\u57ce\u770c","city_name":"\u4ed9\u53f0\u5e02\u592a\u767d\u533a","city_pref":14,"city_detail":"\u5bcc\u6ca2\u5357","zip_code":"9820036"},"26":{"city_order":4,"city_id":14004,"city_pref_name":"\u5bae\u57ce\u770c","city_name":"\u4ed9\u53f0\u5e02\u592a\u767d\u533a","city_pref":14,"city_detail":"\u4f50\u4fdd\u5c71","zip_code":"9820211"},"27":{"city_order":4,"city_id":14004,"city_pref_name":"\u5bae\u57ce\u770c","city_name":"\u4ed9\u53f0\u5e02\u592a\u767d\u533a","city_pref":14,"city_detail":"\u592a\u767d","zip_code":"9820212"},"28":{"city_order":4,"city_id":14004,"city_pref_name":"\u5bae\u57ce\u770c","city_name":"\u4ed9\u53f0\u5e02\u592a\u767d\u533a","city_pref":14,"city_detail":"\u5c71\u7530\u81ea\u7531\u30b1\u4e18","zip_code":"9820213"},"29":{"city_order":4,"city_id":14004,"city_pref_name":"\u5bae\u57ce\u770c","city_name":"\u4ed9\u53f0\u5e02\u592a\u767d\u533a","city_pref":14,"city_detail":"\u5c71\u7530","zip_code":"9820214"},"30":{"city_order":4,"city_id":14004,"city_pref_name":"\u5bae\u57ce\u770c","city_name":"\u4ed9\u53f0\u5e02\u592a\u767d\u533a","city_pref":14,"city_detail":"\u65d7\u7acb","zip_code":"9820215"},"31":{"city_order":4,"city_id":14004,"city_pref_name":"\u5bae\u57ce\u770c","city_name":"\u4ed9\u53f0\u5e02\u592a\u767d\u533a","city_pref":14,"city_detail":"\u65e5\u672c\u5e73","zip_code":"9820221"},"32":{"city_order":4,"city_id":14004,"city_pref_name":"\u5bae\u57ce\u770c","city_name":"\u4ed9\u53f0\u5e02\u592a\u767d\u533a","city_pref":14,"city_detail":"\u4eba\u6765\u7530","zip_code":"9820222"},"33":{"city_order":4,"city_id":14004,"city_pref_name":"\u5bae\u57ce\u770c","city_name":"\u4ed9\u53f0\u5e02\u592a\u767d\u533a","city_pref":14,"city_detail":"\u576a\u6cbc","zip_code":"9820231"},"34":{"city_order":4,"city_id":14004,"city_pref_name":"\u5bae\u57ce\u770c","city_name":"\u4ed9\u53f0\u5e02\u592a\u767d\u533a","city_pref":14,"city_detail":"\u79cb\u4fdd\u753a\u6e6f\u5143","zip_code":"9820241"},"35":{"city_order":4,"city_id":14004,"city_pref_name":"\u5bae\u57ce\u770c","city_name":"\u4ed9\u53f0\u5e02\u592a\u767d\u533a","city_pref":14,"city_detail":"\u79cb\u4fdd\u753a\u5883\u91ce","zip_code":"9820242"},"36":{"city_order":4,"city_id":14004,"city_pref_name":"\u5bae\u57ce\u770c","city_name":"\u4ed9\u53f0\u5e02\u592a\u767d\u533a","city_pref":14,"city_detail":"\u79cb\u4fdd\u753a\u9577\u888b","zip_code":"9820243"},"37":{"city_order":4,"city_id":14004,"city_pref_name":"\u5bae\u57ce\u770c","city_name":"\u4ed9\u53f0\u5e02\u592a\u767d\u533a","city_pref":14,"city_detail":"\u79cb\u4fdd\u753a\u99ac\u5834","zip_code":"9820244"},"38":{"city_order":4,"city_id":14004,"city_pref_name":"\u5bae\u57ce\u770c","city_name":"\u4ed9\u53f0\u5e02\u592a\u767d\u533a","city_pref":14,"city_detail":"\u79cb\u4fdd\u753a\u6e6f\u5411","zip_code":"9820245"},"39":{"city_order":4,"city_id":14004,"city_pref_name":"\u5bae\u57ce\u770c","city_name":"\u4ed9\u53f0\u5e02\u592a\u767d\u533a","city_pref":14,"city_detail":"\u8302\u5ead","zip_code":"9820251"},"40":{"city_order":4,"city_id":14004,"city_pref_name":"\u5bae\u57ce\u770c","city_name":"\u4ed9\u53f0\u5e02\u592a\u767d\u533a","city_pref":14,"city_detail":"\u8302\u5ead\u53f0","zip_code":"9820252"},"41":{"city_order":1,"city_id":14001,"city_pref_name":"\u5bae\u57ce\u770c","city_name":"\u4ed9\u53f0\u5e02\u9752\u8449\u533a","city_pref":14,"city_detail":"\u6298\u7acb","zip_code":"9820261"},"42":{"city_order":1,"city_id":14001,"city_pref_name":"\u5bae\u57ce\u770c","city_name":"\u4ed9\u53f0\u5e02\u9752\u8449\u533a","city_pref":14,"city_detail":"\u897f\u82b1\u82d1","zip_code":"9820262"},"43":{"city_order":1,"city_id":14001,"city_pref_name":"\u5bae\u57ce\u770c","city_name":"\u4ed9\u53f0\u5e02\u9752\u8449\u533a","city_pref":14,"city_detail":"\u8302\u5ead","zip_code":"9820263"},"44":{"city_order":4,"city_id":14004,"city_pref_name":"\u5bae\u57ce\u770c","city_name":"\u4ed9\u53f0\u5e02\u592a\u767d\u533a","city_pref":14,"city_detail":"\u516b\u6728\u5c71\u672c\u753a","zip_code":"9820801"},"45":{"city_order":4,"city_id":14004,"city_pref_name":"\u5bae\u57ce\u770c","city_name":"\u4ed9\u53f0\u5e02\u592a\u767d\u533a","city_pref":14,"city_detail":"\u516b\u6728\u5c71\u6771","zip_code":"9820802"},"46":{"city_order":4,"city_id":14004,"city_pref_name":"\u5bae\u57ce\u770c","city_name":"\u4ed9\u53f0\u5e02\u592a\u767d\u533a","city_pref":14,"city_detail":"\u91d1\u525b\u6ca2","zip_code":"9820803"},"47":{"city_order":4,"city_id":14004,"city_pref_name":"\u5bae\u57ce\u770c","city_name":"\u4ed9\u53f0\u5e02\u592a\u767d\u533a","city_pref":14,"city_detail":"\u920e\u53d6","zip_code":"9820804"},"48":{"city_order":4,"city_id":14004,"city_pref_name":"\u5bae\u57ce\u770c","city_name":"\u4ed9\u53f0\u5e02\u592a\u767d\u533a","city_pref":14,"city_detail":"\u920e\u53d6\u672c\u753a","zip_code":"9820805"},"49":{"city_order":4,"city_id":14004,"city_pref_name":"\u5bae\u57ce\u770c","city_name":"\u4ed9\u53f0\u5e02\u592a\u767d\u533a","city_pref":14,"city_detail":"\u5fa1\u5802\u5e73","zip_code":"9820806"},"50":{"city_order":4,"city_id":14004,"city_pref_name":"\u5bae\u57ce\u770c","city_name":"\u4ed9\u53f0\u5e02\u592a\u767d\u533a","city_pref":14,"city_detail":"\u516b\u6728\u5c71\u5357","zip_code":"9820807"},"51":{"city_order":4,"city_id":14004,"city_pref_name":"\u5bae\u57ce\u770c","city_name":"\u4ed9\u53f0\u5e02\u592a\u767d\u533a","city_pref":14,"city_detail":"\u3072\u3088\u308a\u53f0","zip_code":"9820811"},"52":{"city_order":4,"city_id":14004,"city_pref_name":"\u5bae\u57ce\u770c","city_name":"\u4ed9\u53f0\u5e02\u592a\u767d\u533a","city_pref":14,"city_detail":"\u4e0a\u91ce\u5c71","zip_code":"9820812"},"53":{"city_order":4,"city_id":14004,"city_pref_name":"\u5bae\u57ce\u770c","city_name":"\u4ed9\u53f0\u5e02\u592a\u767d\u533a","city_pref":14,"city_detail":"\u5c71\u7530\u5317\u524d\u753a","zip_code":"9820813"},"54":{"city_order":4,"city_id":14004,"city_pref_name":"\u5bae\u57ce\u770c","city_name":"\u4ed9\u53f0\u5e02\u592a\u767d\u533a","city_pref":14,"city_detail":"\u5c71\u7530","zip_code":"9820814"},"55":{"city_order":4,"city_id":14004,"city_pref_name":"\u5bae\u57ce\u770c","city_name":"\u4ed9\u53f0\u5e02\u592a\u767d\u533a","city_pref":14,"city_detail":"\u5c71\u7530\u4e0a\u30ce\u53f0\u753a","zip_code":"9820815"},"56":{"city_order":4,"city_id":14004,"city_pref_name":"\u5bae\u57ce\u770c","city_name":"\u4ed9\u53f0\u5e02\u592a\u767d\u533a","city_pref":14,"city_detail":"\u5c71\u7530\u672c\u753a","zip_code":"9820816"},"57":{"city_order":4,"city_id":14004,"city_pref_name":"\u5bae\u57ce\u770c","city_name":"\u4ed9\u53f0\u5e02\u592a\u767d\u533a","city_pref":14,"city_detail":"\u7fbd\u9ed2\u53f0","zip_code":"9820817"},"58":{"city_order":4,"city_id":14004,"city_pref_name":"\u5bae\u57ce\u770c","city_name":"\u4ed9\u53f0\u5e02\u592a\u767d\u533a","city_pref":14,"city_detail":"\u5c71\u7530\u65b0\u753a","zip_code":"9820818"},"59":{"city_order":4,"city_id":14004,"city_pref_name":"\u5bae\u57ce\u770c","city_name":"\u4ed9\u53f0\u5e02\u592a\u767d\u533a","city_pref":14,"city_detail":"\u677e\u304c\u4e18","zip_code":"9820821"},"60":{"city_order":4,"city_id":14004,"city_pref_name":"\u5bae\u57ce\u770c","city_name":"\u4ed9\u53f0\u5e02\u592a\u767d\u533a","city_pref":14,"city_detail":"\u82e5\u8449\u753a","zip_code":"9820822"},"61":{"city_order":4,"city_id":14004,"city_pref_name":"\u5bae\u57ce\u770c","city_name":"\u4ed9\u53f0\u5e02\u592a\u767d\u533a","city_pref":14,"city_detail":"\u6075\u548c\u753a","zip_code":"9820823"},"62":{"city_order":4,"city_id":14004,"city_pref_name":"\u5bae\u57ce\u770c","city_name":"\u4ed9\u53f0\u5e02\u592a\u767d\u533a","city_pref":14,"city_detail":"\u82a6\u306e\u53e3","zip_code":"9820824"},"63":{"city_order":4,"city_id":14004,"city_pref_name":"\u5bae\u57ce\u770c","city_name":"\u4ed9\u53f0\u5e02\u592a\u767d\u533a","city_pref":14,"city_detail":"\u897f\u306e\u5e73","zip_code":"9820825"},"64":{"city_order":4,"city_id":14004,"city_pref_name":"\u5bae\u57ce\u770c","city_name":"\u4ed9\u53f0\u5e02\u592a\u767d\u533a","city_pref":14,"city_detail":"\u4e09\u795e\u5cef","zip_code":"9820826"},"65":{"city_order":4,"city_id":14004,"city_pref_name":"\u5bae\u57ce\u770c","city_name":"\u4ed9\u53f0\u5e02\u592a\u767d\u533a","city_pref":14,"city_detail":"\u516b\u6728\u5c71\u9999\u6f84\u753a","zip_code":"9820831"},"66":{"city_order":4,"city_id":14004,"city_pref_name":"\u5bae\u57ce\u770c","city_name":"\u4ed9\u53f0\u5e02\u592a\u767d\u533a","city_pref":14,"city_detail":"\u516b\u6728\u5c71\u7dd1\u753a","zip_code":"9820832"},"67":{"city_order":4,"city_id":14004,"city_pref_name":"\u5bae\u57ce\u770c","city_name":"\u4ed9\u53f0\u5e02\u592a\u767d\u533a","city_pref":14,"city_detail":"\u516b\u6728\u5c71\u5f25\u751f\u753a","zip_code":"9820833"},"68":{"city_order":4,"city_id":14004,"city_pref_name":"\u5bae\u57ce\u770c","city_name":"\u4ed9\u53f0\u5e02\u592a\u767d\u533a","city_pref":14,"city_detail":"\u9752\u5c71","zip_code":"9820834"},"69":{"city_order":4,"city_id":14004,"city_pref_name":"\u5bae\u57ce\u770c","city_name":"\u4ed9\u53f0\u5e02\u592a\u767d\u533a","city_pref":14,"city_detail":"\u685c\u6728\u753a","zip_code":"9820835"},"70":{"city_order":4,"city_id":14004,"city_pref_name":"\u5bae\u57ce\u770c","city_name":"\u4ed9\u53f0\u5e02\u592a\u767d\u533a","city_pref":14,"city_detail":"\u516b\u6728\u5c71\u677e\u6ce2\u753a","zip_code":"9820836"},"71":{"city_order":4,"city_id":14004,"city_pref_name":"\u5bae\u57ce\u770c","city_name":"\u4ed9\u53f0\u5e02\u592a\u767d\u533a","city_pref":14,"city_detail":"\u9577\u753a","zip_code":"9820837"},"72":{"city_order":4,"city_id":14004,"city_pref_name":"\u5bae\u57ce\u770c","city_name":"\u4ed9\u53f0\u5e02\u592a\u767d\u533a","city_pref":14,"city_detail":"\u5411\u5c71","zip_code":"9820841"},"73":{"city_order":4,"city_id":14004,"city_pref_name":"\u5bae\u57ce\u770c","city_name":"\u4ed9\u53f0\u5e02\u592a\u767d\u533a","city_pref":14,"city_detail":"\u8d8a\u8def","zip_code":"9820842"},"74":{"city_order":4,"city_id":14004,"city_pref_name":"\u5bae\u57ce\u770c","city_name":"\u4ed9\u53f0\u5e02\u592a\u767d\u533a","city_pref":14,"city_detail":"\u8302\u30b1\u5d0e","zip_code":"9820843"},"75":{"city_order":4,"city_id":14004,"city_pref_name":"\u5bae\u57ce\u770c","city_name":"\u4ed9\u53f0\u5e02\u592a\u767d\u533a","city_pref":14,"city_detail":"\u6839\u5cb8\u753a","zip_code":"9820844"},"76":{"city_order":4,"city_id":14004,"city_pref_name":"\u5bae\u57ce\u770c","city_name":"\u4ed9\u53f0\u5e02\u592a\u767d\u533a","city_pref":14,"city_detail":"\u9580\u524d\u753a","zip_code":"9820845"},"77":{"city_order":4,"city_id":14004,"city_pref_name":"\u5bae\u57ce\u770c","city_name":"\u4ed9\u53f0\u5e02\u592a\u767d\u533a","city_pref":14,"city_detail":"\u4e8c\u30c4\u6ca2","zip_code":"9820846"},"78":{"city_order":4,"city_id":14004,"city_pref_name":"\u5bae\u57ce\u770c","city_name":"\u4ed9\u53f0\u5e02\u592a\u767d\u533a","city_pref":14,"city_detail":"\u9577\u5dba","zip_code":"9820847"},"79":{"city_order":4,"city_id":14004,"city_pref_name":"\u5bae\u57ce\u770c","city_name":"\u4ed9\u53f0\u5e02\u592a\u767d\u533a","city_pref":14,"city_detail":"\u8429\u30b1\u4e18","zip_code":"9820848"},"city_list":{"14001":"\u4ed9\u53f0\u5e02\u9752\u8449\u533a","14002":"\u4ed9\u53f0\u5e02\u5bae\u57ce\u91ce\u533a","14003":"\u4ed9\u53f0\u5e02\u82e5\u6797\u533a","14004":"\u4ed9\u53f0\u5e02\u592a\u767d\u533a","14005":"\u4ed9\u53f0\u5e02\u6cc9\u533a","14006":"\u77f3\u5dfb\u5e02","14007":"\u5869\u7ac8\u5e02","14008":"\u6c17\u4ed9\u6cbc\u5e02","14009":"\u767d\u77f3\u5e02","14010":"\u540d\u53d6\u5e02","14011":"\u89d2\u7530\u5e02","14012":"\u591a\u8cc0\u57ce\u5e02","14013":"\u5ca9\u6cbc\u5e02","14014":"\u767b\u7c73\u5e02","14015":"\u6817\u539f\u5e02","14016":"\u6771\u677e\u5cf6\u5e02","14017":"\u5927\u5d0e\u5e02","14018":"\u5208\u7530\u90e1\u8535\u738b\u753a","14019":"\u5208\u7530\u90e1\u4e03\u30f6\u5bbf\u753a","14020":"\u67f4\u7530\u90e1\u5927\u6cb3\u539f\u753a","14021":"\u67f4\u7530\u90e1\u6751\u7530\u753a","14022":"\u67f4\u7530\u90e1\u67f4\u7530\u753a","14023":"\u67f4\u7530\u90e1\u5ddd\u5d0e\u753a","14024":"\u4f0a\u5177\u90e1\u4e38\u68ee\u753a","14025":"\u4e98\u7406\u90e1\u4e98\u7406\u753a","14026":"\u4e98\u7406\u90e1\u5c71\u5143\u753a","14027":"\u5bae\u57ce\u90e1\u677e\u5cf6\u753a","14028":"\u5bae\u57ce\u90e1\u4e03\u30f6\u6d5c\u753a","14029":"\u5bae\u57ce\u90e1\u5229\u5e9c\u753a","14030":"\u9ed2\u5ddd\u90e1\u5927\u548c\u753a","14031":"\u9ed2\u5ddd\u90e1\u5927\u90f7\u753a","14032":"\u5bcc\u8c37\u5e02","14033":"\u9ed2\u5ddd\u90e1\u5927\u8861\u6751","14034":"\u52a0\u7f8e\u90e1\u8272\u9ebb\u753a","14035":"\u52a0\u7f8e\u90e1\u52a0\u7f8e\u753a","14036":"\u9060\u7530\u90e1\u6d8c\u8c37\u753a","14037":"\u9060\u7530\u90e1\u7f8e\u91cc\u753a","14038":"\u7261\u9e7f\u90e1\u5973\u5ddd\u753a","14039":"\u672c\u5409\u90e1\u5357\u4e09\u9678\u753a","14999":"\uff08\u65e7\u4f4f\u6240\uff09"}}